{
  "GTK::Raw::AppChooser": {
    "ast": 0e0,
    "optimize": 0.001e0,
    "syntaxcheck": 0e0,
    "start": 0e0,
    "parse": 2.949e0,
    "moar": 0e0,
    "mast": 0.003e0,
    "mbc": 0.001e0
  },
  "GTK::Roles::Signals::EntryBuffer": {
    "syntaxcheck": 0e0,
    "optimize": 0.001e0,
    "ast": 0e0,
    "mast": 0.003e0,
    "mbc": 0e0,
    "parse": 2.937e0,
    "start": 0e0,
    "moar": 0e0
  },
  "GTK::Raw::PageSetup": {
    "syntaxcheck": 0e0,
    "ast": 0e0,
    "optimize": 0.001e0,
    "mbc": 0.001e0,
    "mast": 0.004e0,
    "moar": 0e0,
    "start": 0e0,
    "parse": 4.669e0
  },
  "GTK::Raw::TargetEntry": {
    "mbc": 0.001e0,
    "mast": 0.003e0,
    "parse": 2.909e0,
    "start": 0e0,
    "moar": 0e0,
    "syntaxcheck": 0e0,
    "ast": 0e0,
    "optimize": 0.001e0
  },
  "GTK::Roles::ToolShell": {
    "syntaxcheck": 0e0,
    "ast": 0e0,
    "optimize": 0.001e0,
    "mbc": 0.001e0,
    "mast": 0.003e0,
    "moar": 0e0,
    "parse": 3.263e0,
    "start": 0e0
  },
  "GTK::Compat::Raw::Cairo": {
    "ast": 0e0,
    "optimize": 0.001e0,
    "syntaxcheck": 0e0,
    "moar": 0e0,
    "start": 0e0,
    "parse": 3.682e0,
    "mbc": 0.001e0,
    "mast": 0.003e0
  },
  "GTK::Raw::WindowGroup": {
    "syntaxcheck": 0e0,
    "ast": 0e0,
    "optimize": 0.002e0,
    "mbc": 0.001e0,
    "mast": 0.007e0,
    "start": 0e0,
    "parse": 3.02e0,
    "moar": 0e0
  },
  "GTK::Raw::Window": {
    "moar": 0e0,
    "parse": 11.05e0,
    "start": 0e0,
    "mast": 0.006e0,
    "mbc": 0.002e0,
    "optimize": 0.003e0,
    "ast": 0e0,
    "syntaxcheck": 0e0
  },
  "GTK::Raw::Scrollbar": {
    "syntaxcheck": 0e0,
    "ast": 0e0,
    "optimize": 0.001e0,
    "mast": 0.003e0,
    "mbc": 0.001e0,
    "moar": 0e0,
    "start": 0e0,
    "parse": 2.754e0
  },
  "GTK::Roles::FileChooser": {
    "parse": 3.727e0,
    "start": 0e0,
    "moar": 0e0,
    "mast": 0.003e0,
    "mbc": 0.001e0,
    "ast": 0e0,
    "optimize": 0.001e0,
    "syntaxcheck": 0e0
  },
  "GTK::FontButton": {
    "moar": 0e0,
    "start": 0e0,
    "parse": 4.311e0,
    "mbc": 0.001e0,
    "mast": 0.017e0,
    "optimize": 0.001e0,
    "ast": 0e0,
    "syntaxcheck": 0e0
  },
  "GTK::Builder::ToggleButton": {
    "start": 0e0,
    "parse": 2.125e0,
    "moar": 0e0,
    "mast": 0.008e0,
    "mbc": 0.001e0,
    "ast": 0e0,
    "optimize": 0.002e0,
    "syntaxcheck": 0e0
  },
  "GTK::Compat::LaunchContext": {
    "mbc": 0.001e0,
    "mast": 0.008e0,
    "start": 0e0,
    "parse": 2.642e0,
    "moar": 0e0,
    "syntaxcheck": 0e0,
    "optimize": 0.002e0,
    "ast": 0e0
  },
  "GTK::Raw::Orientable": {
    "mbc": 0.001e0,
    "mast": 0.003e0,
    "moar": 0e0,
    "start": 0e0,
    "parse": 2.776e0,
    "syntaxcheck": 0e0,
    "ast": 0e0,
    "optimize": 0.001e0
  },
  "GTK::Adjustment": {
    "start": 0e0,
    "parse": 2.992e0,
    "moar": 0e0,
    "mast": 0.003e0,
    "mbc": 0.001e0,
    "optimize": 0.001e0,
    "ast": 0e0,
    "syntaxcheck": 0e0
  },
  "GTK::Compat::Permission": {
    "start": 0e0,
    "parse": 2.895e0,
    "moar": 0e0,
    "mast": 0.003e0,
    "mbc": 0.001e0,
    "optimize": 0.001e0,
    "ast": 0e0,
    "syntaxcheck": 0e0
  },
  "GTK::Builder::LinkButton": {
    "mbc": 0.001e0,
    "mast": 0.013e0,
    "moar": 0e0,
    "parse": 2.118e0,
    "start": 0e0,
    "syntaxcheck": 0e0,
    "optimize": 0.002e0,
    "ast": 0e0
  },
  "GTK::Compat::Raw::Array": {
    "parse": 5.085e0,
    "start": 0e0,
    "moar": 0e0,
    "mast": 0.009e0,
    "mbc": 0.002e0,
    "ast": 0e0,
    "optimize": 0.003e0,
    "syntaxcheck": 0e0
  },
  "GTK::Raw::ToolPalette": {
    "mast": 0.003e0,
    "mbc": 0.001e0,
    "moar": 0e0,
    "parse": 4.11e0,
    "start": 0e0,
    "syntaxcheck": 0e0,
    "ast": 0e0,
    "optimize": 0.001e0
  },
  "GTK::Raw::Layout": {
    "mbc": 0.001e0,
    "mast": 0.008e0,
    "parse": 3.348e0,
    "start": 0e0,
    "moar": 0e0,
    "syntaxcheck": 0e0,
    "ast": 0e0,
    "optimize": 0.002e0
  },
  "GTK::Roles::Editable": {
    "syntaxcheck": 0e0,
    "optimize": 0.001e0,
    "ast": 0e0,
    "mast": 0.003e0,
    "mbc": 0.001e0,
    "moar": 0e0,
    "parse": 3.084e0,
    "start": 0e0
  },
  "GTK::Compat::FrameClock": {
    "syntaxcheck": 0e0,
    "ast": 0e0,
    "optimize": 0.001e0,
    "mast": 0.003e0,
    "mbc": 0e0,
    "moar": 0e0,
    "start": 0e0,
    "parse": 2.82e0
  },
  "GTK::Revealer": {
    "ast": 0e0,
    "optimize": 0.001e0,
    "syntaxcheck": 0e0,
    "moar": 0e0,
    "parse": 3.994e0,
    "start": 0e0,
    "mast": 0.003e0,
    "mbc": 0.001e0
  },
  "GTK::Dialog::Raw::About": {
    "ast": 0e0,
    "optimize": 0.001e0,
    "syntaxcheck": 0e0,
    "moar": 0e0,
    "parse": 4.988e0,
    "start": 0e0,
    "mbc": 0.001e0,
    "mast": 0.003e0
  },
  "GTK::ColorButton": {
    "moar": 0e0,
    "start": 0e0,
    "parse": 4.199e0,
    "mbc": 0.001e0,
    "mast": 0.003e0,
    "ast": 0e0,
    "optimize": 0.012e0,
    "syntaxcheck": 0e0
  },
  "GTK::Compat::Raw::GSList": {
    "ast": 0e0,
    "optimize": 0.001e0,
    "syntaxcheck": 0e0,
    "moar": 0e0,
    "parse": 4.113e0,
    "start": 0e0,
    "mast": 0.004e0,
    "mbc": 0.001e0
  },
  "GTK::TextIter": {
    "mbc": 0e0,
    "mast": 0.003e0,
    "moar": 0e0,
    "parse": 3.688e0,
    "start": 0e0,
    "syntaxcheck": 0e0,
    "optimize": 0.001e0,
    "ast": 0e0
  },
  "GTK::Entry": {
    "syntaxcheck": 0e0,
    "ast": 0e0,
    "optimize": 0.001e0,
    "mbc": 0.001e0,
    "mast": 0.003e0,
    "moar": 0e0,
    "parse": 4.754e0,
    "start": 0e0
  },
  "GTK::Dialog::PageSetupUnix": {
    "mbc": 0.001e0,
    "mast": 0.004e0,
    "parse": 4.335e0,
    "start": 0e0,
    "moar": 0e0,
    "syntaxcheck": 0e0,
    "optimize": 0.002e0,
    "ast": 0e0
  },
  "GTK::AccelLabel": {
    "moar": 0e0,
    "start": 0e0,
    "parse": 3.889e0,
    "mbc": 0.001e0,
    "mast": 0.003e0,
    "optimize": 0.001e0,
    "ast": 0e0,
    "syntaxcheck": 0e0
  },
  "GTK::Raw::Entry": {
    "syntaxcheck": 0e0,
    "ast": 0e0,
    "optimize": 0.002e0,
    "mbc": 0.001e0,
    "mast": 0.005e0,
    "start": 0e0,
    "parse": 8.287e0,
    "moar": 0e0
  },
  "GTK::Raw::Actionable": {
    "syntaxcheck": 0e0,
    "ast": 0e0,
    "optimize": 0.001e0,
    "mast": 0.003e0,
    "mbc": 0.001e0,
    "start": 0e0,
    "parse": 2.942e0,
    "moar": 0e0
  },
  "GTK::TreeViewColumn": {
    "mbc": 0.001e0,
    "mast": 0.003e0,
    "parse": 4.502e0,
    "start": 0e0,
    "moar": 0e0,
    "syntaxcheck": 0e0,
    "ast": 0e0,
    "optimize": 0.001e0
  },
  "GTK::ComboBox": {
    "syntaxcheck": 0e0,
    "optimize": 0.014e0,
    "ast": 0e0,
    "mbc": 0.001e0,
    "mast": 0.003e0,
    "parse": 4.99e0,
    "start": 0e0,
    "moar": 0e0
  },
  "GTK::ShortcutsSection": {
    "optimize": 0.002e0,
    "ast": 0e0,
    "syntaxcheck": 0e0,
    "moar": 0e0,
    "parse": 3.896e0,
    "start": 0e0,
    "mast": 0.026e0,
    "mbc": 0.001e0
  },
  "GTK::Raw::CellView": {
    "ast": 0e0,
    "optimize": 0.002e0,
    "syntaxcheck": 0e0,
    "moar": 0e0,
    "start": 0e0,
    "parse": 3.773e0,
    "mast": 0.014e0,
    "mbc": 0.001e0
  },
  "GTK::Compat::MenuAttributeIter": {
    "parse": 2.479e0,
    "start": 0e0,
    "moar": 0e0,
    "mast": 0.003e0,
    "mbc": 0.001e0,
    "optimize": 0.001e0,
    "ast": 0e0,
    "syntaxcheck": 0e0
  },
  "GTK::Roles::Signals::Menu": {
    "syntaxcheck": 0e0,
    "optimize": 0.001e0,
    "ast": 0e0,
    "mast": 0.003e0,
    "mbc": 0e0,
    "parse": 2.933e0,
    "start": 0e0,
    "moar": 0e0
  },
  "GTK::Raw::TreeSortable": {
    "parse": 3.116e0,
    "start": 0e0,
    "moar": 0e0,
    "mast": 0.003e0,
    "mbc": 0.001e0,
    "optimize": 0.001e0,
    "ast": 0e0,
    "syntaxcheck": 0e0
  },
  "GTK::Raw::CellAreaBox": {
    "mast": 0.007e0,
    "mbc": 0.001e0,
    "start": 0e0,
    "parse": 2.965e0,
    "moar": 0e0,
    "syntaxcheck": 0e0,
    "optimize": 0.002e0,
    "ast": 0e0
  },
  "GTK::RadioButton": {
    "mast": 0.003e0,
    "mbc": 0.001e0,
    "moar": 0e0,
    "parse": 4.317e0,
    "start": 0e0,
    "syntaxcheck": 0e0,
    "optimize": 0.001e0,
    "ast": 0e0
  },
  "GTK::Assistant": {
    "moar": 0e0,
    "parse": 4.452e0,
    "start": 0e0,
    "mast": 0.003e0,
    "mbc": 0.001e0,
    "ast": 0e0,
    "optimize": 0.001e0,
    "syntaxcheck": 0e0
  },
  "GTK::Raw::PrintContext": {
    "moar": 0e0,
    "parse": 3.576e0,
    "start": 0e0,
    "mbc": 0.001e0,
    "mast": 0.003e0,
    "ast": 0e0,
    "optimize": 0.001e0,
    "syntaxcheck": 0e0
  },
  "GTK::Compat::MenuItem": {
    "mbc": 0.001e0,
    "mast": 0.013e0,
    "moar": 0e0,
    "start": 0e0,
    "parse": 2.685e0,
    "syntaxcheck": 0e0,
    "optimize": 0.002e0,
    "ast": 0e0
  },
  "GTK::Compat::Menu": {
    "mast": 0.008e0,
    "mbc": 0.001e0,
    "moar": 0e0,
    "start": 0e0,
    "parse": 2.809e0,
    "syntaxcheck": 0e0,
    "optimize": 0.002e0,
    "ast": 0e0
  },
  "GTK::Builder::Button": {
    "syntaxcheck": 0e0,
    "optimize": 0.002e0,
    "ast": 0e0,
    "mast": 0.008e0,
    "mbc": 0.001e0,
    "start": 0e0,
    "parse": 2.213e0,
    "moar": 0e0
  },
  "GTK::Popover": {
    "ast": 0e0,
    "optimize": 0.001e0,
    "syntaxcheck": 0e0,
    "moar": 0e0,
    "start": 0e0,
    "parse": 4.088e0,
    "mbc": 0.001e0,
    "mast": 0.003e0
  },
  "GTK::Raw::FontChooser": {
    "mast": 0.003e0,
    "mbc": 0.001e0,
    "start": 0e0,
    "parse": 3.69e0,
    "moar": 0e0,
    "syntaxcheck": 0e0,
    "ast": 0e0,
    "optimize": 0.001e0
  },
  "Pluggable": {
    "moar": 0e0,
    "start": 0e0,
    "parse": 4.371e0,
    "mast": 0.008e0,
    "mbc": 0.001e0,
    "optimize": 0.002e0,
    "ast": 0e0,
    "syntaxcheck": 0e0
  },
  "GTK::Compat::FrameTimings": {
    "mbc": 0.001e0,
    "mast": 0.008e0,
    "parse": 2.505e0,
    "start": 0e0,
    "moar": 0e0,
    "syntaxcheck": 0e0,
    "ast": 0e0,
    "optimize": 0.002e0
  },
  "GTK::ScaleButton": {
    "syntaxcheck": 0e0,
    "optimize": 0.001e0,
    "ast": 0e0,
    "mbc": 0.012e0,
    "mast": 0.003e0,
    "moar": 0e0,
    "parse": 4.238e0,
    "start": 0e0
  },
  "GTK::Raw::MenuButton": {
    "mast": 0.004e0,
    "mbc": 0.001e0,
    "moar": 0e0,
    "parse": 3.502e0,
    "start": 0e0,
    "syntaxcheck": 0e0,
    "optimize": 0.001e0,
    "ast": 0e0
  },
  "GTK::Compat::Raw::Keymap": {
    "mast": 0.008e0,
    "mbc": 0.001e0,
    "moar": 0e0,
    "parse": 3.709e0,
    "start": 0e0,
    "syntaxcheck": 0e0,
    "optimize": 0.002e0,
    "ast": 0e0
  },
  "GTK::Compat::AppLaunchContext": {
    "ast": 0e0,
    "optimize": 0.002e0,
    "syntaxcheck": 0e0,
    "start": 0e0,
    "parse": 2.946e0,
    "moar": 0e0,
    "mbc": 0.001e0,
    "mast": 0.008e0
  },
  "GTK::Raw::Settings": {
    "syntaxcheck": 0e0,
    "optimize": 0.002e0,
    "ast": 0e0,
    "mbc": 0.001e0,
    "mast": 0.008e0,
    "moar": 0e0,
    "parse": 3.72e0,
    "start": 0e0
  },
  "GTK::Raw::Range": {
    "mbc": 0.001e0,
    "mast": 0.004e0,
    "parse": 4.653e0,
    "start": 0e0,
    "moar": 0e0,
    "syntaxcheck": 0e0,
    "ast": 0e0,
    "optimize": 0.001e0
  },
  "GTK::Roles::Signals::Entry": {
    "ast": 0e0,
    "optimize": 0.001e0,
    "syntaxcheck": 0e0,
    "start": 0e0,
    "parse": 2.841e0,
    "moar": 0e0,
    "mast": 0.003e0,
    "mbc": 0e0
  },
  "GTK::Roles::Signals::Notebook": {
    "syntaxcheck": 0e0,
    "optimize": 0.001e0,
    "ast": 0e0,
    "mbc": 0e0,
    "mast": 0.003e0,
    "moar": 0e0,
    "start": 0e0,
    "parse": 3.356e0
  },
  "GTK::CellRendererSpin": {
    "parse": 3.04e0,
    "start": 0e0,
    "moar": 0e0,
    "mbc": 0.001e0,
    "mast": 0.009e0,
    "ast": 0e0,
    "optimize": 0.002e0,
    "syntaxcheck": 0e0
  },
  "GTK::Compat::Seat": {
    "mast": 0.007e0,
    "mbc": 0.001e0,
    "start": 0e0,
    "parse": 3.174e0,
    "moar": 0e0,
    "syntaxcheck": 0e0,
    "ast": 0e0,
    "optimize": 0.002e0
  },
  "GTK::SearchBar": {
    "syntaxcheck": 0e0,
    "ast": 0e0,
    "optimize": 0.001e0,
    "mast": 0.003e0,
    "mbc": 0.001e0,
    "start": 0e0,
    "parse": 3.923e0,
    "moar": 0e0
  },
  "GTK::Switch": {
    "ast": 0e0,
    "optimize": 0.001e0,
    "syntaxcheck": 0e0,
    "start": 0e0,
    "parse": 3.769e0,
    "moar": 0e0,
    "mast": 0.003e0,
    "mbc": 0.001e0
  },
  "GTK::Raw::Pane": {
    "syntaxcheck": 0e0,
    "ast": 0e0,
    "optimize": 0.001e0,
    "mbc": 0.001e0,
    "mast": 0.003e0,
    "moar": 0e0,
    "parse": 3.57e0,
    "start": 0e0
  },
  "GTK::Raw::Popover": {
    "mast": 0.004e0,
    "mbc": 0.001e0,
    "moar": 0e0,
    "start": 0e0,
    "parse": 4.066e0,
    "syntaxcheck": 0e0,
    "optimize": 0.001e0,
    "ast": 0e0
  },
  "GTK::SizeGroup": {
    "moar": 0e0,
    "start": 0e0,
    "parse": 2.836e0,
    "mbc": 0e0,
    "mast": 0.003e0,
    "ast": 0e0,
    "optimize": 0.001e0,
    "syntaxcheck": 0e0
  },
  "GTK::Raw::CellRendererText": {
    "syntaxcheck": 0e0,
    "ast": 0e0,
    "optimize": 0.001e0,
    "mbc": 0.001e0,
    "mast": 0.003e0,
    "start": 0e0,
    "parse": 2.837e0,
    "moar": 0e0
  },
  "GTK::EventBox": {
    "syntaxcheck": 0e0,
    "optimize": 0.001e0,
    "ast": 0e0,
    "mast": 0.003e0,
    "mbc": 0.001e0,
    "moar": 0e0,
    "start": 0e0,
    "parse": 3.931e0
  },
  "GTK::Raw::ColorButton": {
    "syntaxcheck": 0e0,
    "optimize": 0.002e0,
    "ast": 0e0,
    "mast": 0.004e0,
    "mbc": 0.001e0,
    "moar": 0e0,
    "parse": 3.577e0,
    "start": 0e0
  },
  "GTK::Raw::CellRendererSpin": {
    "ast": 0e0,
    "optimize": 0.002e0,
    "syntaxcheck": 0e0,
    "start": 0e0,
    "parse": 2.711e0,
    "moar": 0e0,
    "mast": 0.014e0,
    "mbc": 0.001e0
  },
  "GTK::Roles::Signals::Range": {
    "mbc": 0.001e0,
    "mast": 0.003e0,
    "moar": 0e0,
    "start": 0e0,
    "parse": 2.942e0,
    "syntaxcheck": 0e0,
    "optimize": 0.003e0,
    "ast": 0e0
  },
  "GTK::EntryBuffer": {
    "moar": 0e0,
    "parse": 3.074e0,
    "start": 0e0,
    "mast": 0.003e0,
    "mbc": 0.001e0,
    "optimize": 0.001e0,
    "ast": 0e0,
    "syntaxcheck": 0e0
  },
  "GTK::Builder::MenuItem": {
    "mbc": 0.001e0,
    "mast": 0.008e0,
    "parse": 2.326e0,
    "start": 0e0,
    "moar": 0e0,
    "syntaxcheck": 0e0,
    "optimize": 0.002e0,
    "ast": 0e0
  },
  "Pango::FontMap": {
    "mast": 0.003e0,
    "mbc": 0.001e0,
    "moar": 0e0,
    "parse": 4.596e0,
    "start": 0e0,
    "syntaxcheck": 0e0,
    "optimize": 0.001e0,
    "ast": 0e0
  },
  "GTK::Layout": {
    "ast": 0e0,
    "optimize": 0.002e0,
    "syntaxcheck": 0e0,
    "start": 0e0,
    "parse": 3.989e0,
    "moar": 0e0,
    "mast": 0.008e0,
    "mbc": 0.001e0
  },
  "GTK::Bin": {
    "optimize": 0.001e0,
    "ast": 0e0,
    "syntaxcheck": 0e0,
    "parse": 3.847e0,
    "start": 0e0,
    "moar": 0e0,
    "mast": 0.003e0,
    "mbc": 0.001e0
  },
  "GTK::Raw::CheckButton": {
    "mast": 0.003e0,
    "mbc": 0.001e0,
    "parse": 2.847e0,
    "start": 0e0,
    "moar": 0e0,
    "syntaxcheck": 0e0,
    "ast": 0e0,
    "optimize": 0.001e0
  },
  "Method::Also": {
    "syntaxcheck": 0e0,
    "ast": 0e0,
    "optimize": 0.002e0,
    "mbc": 0.001e0,
    "mast": 0.015e0,
    "start": 0e0,
    "parse": 1.083e0,
    "moar": 0e0
  },
  "GTK::Roles::Signals::ListBox": {
    "syntaxcheck": 0e0,
    "ast": 0e0,
    "optimize": 0.002e0,
    "mast": 0.014e0,
    "mbc": 0.001e0,
    "start": 0e0,
    "parse": 2.783e0,
    "moar": 0e0
  },
  "GTK::Raw::Subs": {
    "start": 0e0,
    "parse": 4.899e0,
    "moar": 0e0,
    "mast": 0.004e0,
    "mbc": 0.001e0,
    "ast": 0e0,
    "optimize": 0.001e0,
    "syntaxcheck": 0e0
  },
  "GTK::Label": {
    "moar": 0e0,
    "start": 0e0,
    "parse": 4.75e0,
    "mast": 0.003e0,
    "mbc": 0.001e0,
    "optimize": 0.001e0,
    "ast": 0e0,
    "syntaxcheck": 0e0
  },
  "GTK::Raw::SeparatorMenuItem": {
    "mbc": 0e0,
    "mast": 0.003e0,
    "parse": 2.713e0,
    "start": 0e0,
    "moar": 0e0,
    "syntaxcheck": 0e0,
    "ast": 0e0,
    "optimize": 0.001e0
  },
  "GTK::Notebook": {
    "ast": 0e0,
    "optimize": 0.001e0,
    "syntaxcheck": 0e0,
    "moar": 0e0,
    "start": 0e0,
    "parse": 4.518e0,
    "mast": 0.003e0,
    "mbc": 0.001e0
  },
  "GTK::Compat::Keymap": {
    "ast": 0e0,
    "optimize": 0.002e0,
    "syntaxcheck": 0e0,
    "moar": 0e0,
    "parse": 2.901e0,
    "start": 0e0,
    "mast": 0.008e0,
    "mbc": 0.001e0
  },
  "GTK::WidgetPath": {
    "optimize": 0.001e0,
    "ast": 0e0,
    "syntaxcheck": 0e0,
    "parse": 3.803e0,
    "start": 0e0,
    "moar": 0e0,
    "mast": 0.003e0,
    "mbc": 0.001e0
  },
  "GTK::Stack": {
    "ast": 0e0,
    "optimize": 0.001e0,
    "syntaxcheck": 0e0,
    "moar": 0e0,
    "parse": 4.575e0,
    "start": 0e0,
    "mbc": 0.001e0,
    "mast": 0.003e0
  },
  "GTK::Roles::Signals::CellRenderer": {
    "mbc": 0e0,
    "mast": 0.003e0,
    "start": 0e0,
    "parse": 2.889e0,
    "moar": 0e0,
    "syntaxcheck": 0e0,
    "ast": 0e0,
    "optimize": 0.001e0
  },
  "GTK::Raw::Viewport": {
    "ast": 0e0,
    "optimize": 0.002e0,
    "syntaxcheck": 0e0,
    "moar": 0e0,
    "start": 0e0,
    "parse": 3.275e0,
    "mast": 0.014e0,
    "mbc": 0.001e0
  },
  "GTK::MenuToolButton": {
    "moar": 0e0,
    "start": 0e0,
    "parse": 4.184e0,
    "mbc": 0.001e0,
    "mast": 0.016e0,
    "optimize": 0.001e0,
    "ast": 0e0,
    "syntaxcheck": 0e0
  },
  "GTK::Dialog": {
    "mbc": 0.001e0,
    "mast": 0.003e0,
    "moar": 0e0,
    "parse": 4.52e0,
    "start": 0e0,
    "syntaxcheck": 0e0,
    "optimize": 0.001e0,
    "ast": 0e0
  },
  "GTK::AspectFrame": {
    "start": 0e0,
    "parse": 3.988e0,
    "moar": 0e0,
    "mast": 0.013e0,
    "mbc": 0.006e0,
    "optimize": 0.002e0,
    "ast": 0e0,
    "syntaxcheck": 0e0
  },
  "GTK::Roles::Signals::ScrolledWindow": {
    "moar": 0e0,
    "parse": 2.925e0,
    "start": 0e0,
    "mast": 0.003e0,
    "mbc": 0.001e0,
    "ast": 0e0,
    "optimize": 0.001e0,
    "syntaxcheck": 0e0
  },
  "GTK::Raw::PrintSettings": {
    "mbc": 0.001e0,
    "mast": 0.017e0,
    "parse": 8.641e0,
    "start": 0e0,
    "moar": 0e0,
    "syntaxcheck": 0e0,
    "ast": 0e0,
    "optimize": 0.002e0
  },
  "GTK::CSSProvider": {
    "syntaxcheck": 0e0,
    "ast": 0e0,
    "optimize": 0.001e0,
    "mbc": 0.001e0,
    "mast": 0.003e0,
    "moar": 0e0,
    "start": 0e0,
    "parse": 3.131e0
  },
  "GTK::Range": {
    "mast": 0.003e0,
    "mbc": 0e0,
    "moar": 0e0,
    "start": 0e0,
    "parse": 4.246e0,
    "syntaxcheck": 0e0,
    "ast": 0e0,
    "optimize": 0.001e0
  },
  "GTK::Compat::Raw::DragContext": {
    "start": 0e0,
    "parse": 3.873e0,
    "moar": 0e0,
    "mast": 0.004e0,
    "mbc": 0.001e0,
    "ast": 0e0,
    "optimize": 0.001e0,
    "syntaxcheck": 0e0
  },
  "GTK::LevelBar": {
    "mbc": 0.001e0,
    "mast": 0.003e0,
    "start": 0e0,
    "parse": 3.815e0,
    "moar": 0e0,
    "syntaxcheck": 0e0,
    "optimize": 0.001e0,
    "ast": 0e0
  },
  "GTK::Compat::Raw::Display": {
    "mast": 0.004e0,
    "mbc": 0.001e0,
    "moar": 0e0,
    "start": 0e0,
    "parse": 4.966e0,
    "syntaxcheck": 0e0,
    "ast": 0e0,
    "optimize": 0.002e0
  },
  "DEPENDENCIES": {
    "sys": 1.06e0,
    "user": 14.19e0,
    "real": 12.94e0
  },
  "GTK::Dialog::Raw::FontChooser": {
    "mbc": 0.001e0,
    "mast": 0.003e0,
    "moar": 0e0,
    "start": 0e0,
    "parse": 2.75e0,
    "syntaxcheck": 0e0,
    "ast": 0e0,
    "optimize": 0.001e0
  },
  "GTK::ListBox": {
    "start": 0e0,
    "parse": 4.396e0,
    "moar": 0e0,
    "mbc": 0.001e0,
    "mast": 0.008e0,
    "optimize": 0.002e0,
    "ast": 0e0,
    "syntaxcheck": 0e0
  },
  "GTK::TextView": {
    "syntaxcheck": 0e0,
    "ast": 0e0,
    "optimize": 0.001e0,
    "mbc": 0.001e0,
    "mast": 0.003e0,
    "parse": 5.491e0,
    "start": 0e0,
    "moar": 0e0
  },
  "Pango::Tabs": {
    "mbc": 0.001e0,
    "mast": 0.003e0,
    "moar": 0e0,
    "parse": 4.593e0,
    "start": 0e0,
    "syntaxcheck": 0e0,
    "ast": 0e0,
    "optimize": 0.001e0
  },
  "GTK::Raw::MenuBar": {
    "mast": 0.003e0,
    "mbc": 0.001e0,
    "moar": 0e0,
    "start": 0e0,
    "parse": 3.087e0,
    "syntaxcheck": 0e0,
    "optimize": 0.001e0,
    "ast": 0e0
  },
  "GTK::Raw::TextIter": {
    "optimize": 0.002e0,
    "ast": 0e0,
    "syntaxcheck": 0e0,
    "start": 0e0,
    "parse": 9.34e0,
    "moar": 0e0,
    "mast": 0.005e0,
    "mbc": 0.001e0
  },
  "GTK::PaperSize": {
    "mast": 0.008e0,
    "mbc": 0.001e0,
    "moar": 0e0,
    "start": 0e0,
    "parse": 3.003e0,
    "syntaxcheck": 0e0,
    "ast": 0e0,
    "optimize": 0.001e0
  },
  "GTK::Compat::Roles::Signals::Settings": {
    "optimize": 0.002e0,
    "ast": 0e0,
    "syntaxcheck": 0e0,
    "moar": 0e0,
    "parse": 2.772e0,
    "start": 0e0,
    "mast": 0.007e0,
    "mbc": 0.001e0
  },
  "GTK": {
    "mbc": 0.001e0,
    "mast": 0.003e0,
    "parse": 9.051e0,
    "start": 0e0,
    "moar": 0e0,
    "syntaxcheck": 0e0,
    "ast": 0e0,
    "optimize": 0.001e0
  },
  "GTK::ShortcutsWindow": {
    "ast": 0e0,
    "optimize": 0.002e0,
    "syntaxcheck": 0e0,
    "moar": 0e0,
    "parse": 3.914e0,
    "start": 0e0,
    "mast": 0.008e0,
    "mbc": 0.001e0
  },
  "GTK::Raw::LinkButton": {
    "ast": 0e0,
    "optimize": 0.001e0,
    "syntaxcheck": 0e0,
    "moar": 0e0,
    "parse": 3.097e0,
    "start": 0e0,
    "mast": 0.003e0,
    "mbc": 0.001e0
  },
  "GTK::MenuShell": {
    "optimize": 0.001e0,
    "ast": 0e0,
    "syntaxcheck": 0e0,
    "moar": 0e0,
    "parse": 4.21e0,
    "start": 0e0,
    "mbc": 0.001e0,
    "mast": 0.007e0
  },
  "GTK::Builder::MenuButton": {
    "ast": 0e0,
    "optimize": 0.002e0,
    "syntaxcheck": 0e0,
    "moar": 0e0,
    "start": 0e0,
    "parse": 2.261e0,
    "mast": 0.008e0,
    "mbc": 0.001e0
  },
  "GTK::Statusbar": {
    "optimize": 0.001e0,
    "ast": 0e0,
    "syntaxcheck": 0e0,
    "start": 0e0,
    "parse": 3.993e0,
    "moar": 0e0,
    "mast": 0.003e0,
    "mbc": 0.001e0
  },
  "GTK::Raw::AppButton": {
    "syntaxcheck": 0e0,
    "optimize": 0.001e0,
    "ast": 0e0,
    "mast": 0.003e0,
    "mbc": 0.001e0,
    "moar": 0e0,
    "parse": 3.361e0,
    "start": 0e0
  },
  "GTK::Roles::Pointers": {
    "optimize": 0.001e0,
    "ast": 0e0,
    "syntaxcheck": 0e0,
    "moar": 0e0,
    "parse": 2.309e0,
    "start": 0e0,
    "mbc": 0.001e0,
    "mast": 0.003e0
  },
  "Pango::Context": {
    "mbc": 0e0,
    "mast": 0.003e0,
    "parse": 17.287e0,
    "start": 0e0,
    "moar": 0e0,
    "syntaxcheck": 0e0,
    "ast": 0e0,
    "optimize": 0.001e0
  },
  "GTK::Compat::Event": {
    "syntaxcheck": 0e0,
    "optimize": 0.002e0,
    "ast": 0e0,
    "mast": 0.008e0,
    "mbc": 0.001e0,
    "parse": 3.316e0,
    "start": 0e0,
    "moar": 0e0
  },
  "GTK::Raw::Frame": {
    "mast": 0.003e0,
    "mbc": 0.001e0,
    "start": 0e0,
    "parse": 3.37e0,
    "moar": 0e0,
    "syntaxcheck": 0e0,
    "ast": 0e0,
    "optimize": 0.001e0
  },
  "GTK::CheckMenuItem": {
    "mbc": 0.001e0,
    "mast": 0.003e0,
    "start": 0e0,
    "parse": 4.162e0,
    "moar": 0e0,
    "syntaxcheck": 0e0,
    "optimize": 0.001e0,
    "ast": 0e0
  },
  "GTK::Roles::CellEditable": {
    "mbc": 0e0,
    "mast": 0.003e0,
    "start": 0e0,
    "parse": 2.916e0,
    "moar": 0e0,
    "syntaxcheck": 0e0,
    "optimize": 0.001e0,
    "ast": 0e0
  },
  "GTK::ToolItemGroup": {
    "ast": 0e0,
    "optimize": 0.001e0,
    "syntaxcheck": 0e0,
    "moar": 0e0,
    "parse": 4.332e0,
    "start": 0e0,
    "mast": 0.003e0,
    "mbc": 0.001e0
  },
  "GTK::Raw::AccelLabel": {
    "mast": 0.003e0,
    "mbc": 0.001e0,
    "parse": 3.26e0,
    "start": 0e0,
    "moar": 0e0,
    "syntaxcheck": 0e0,
    "optimize": 0.001e0,
    "ast": 0e0
  },
  "GTK::Raw::LevelBar": {
    "start": 0e0,
    "parse": 3.724e0,
    "moar": 0e0,
    "mast": 0.003e0,
    "mbc": 0.001e0,
    "optimize": 0.001e0,
    "ast": 0e0,
    "syntaxcheck": 0e0
  },
  "GTK::Raw::RadioMenuItem": {
    "parse": 3.316e0,
    "start": 0e0,
    "moar": 0e0,
    "mbc": 0.001e0,
    "mast": 0.003e0,
    "optimize": 0.001e0,
    "ast": 0e0,
    "syntaxcheck": 0e0
  },
  "GTK::TreePath": {
    "mast": 0.003e0,
    "mbc": 0e0,
    "parse": 2.895e0,
    "start": 0e0,
    "moar": 0e0,
    "syntaxcheck": 0e0,
    "ast": 0e0,
    "optimize": 0.001e0
  },
  "GTK::Compat::Cairo": {
    "mbc": 0e0,
    "mast": 0.003e0,
    "moar": 0e0,
    "parse": 2.745e0,
    "start": 0e0,
    "syntaxcheck": 0e0,
    "optimize": 0.001e0,
    "ast": 0e0
  },
  "GTK::Raw::Application": {
    "optimize": 0.001e0,
    "ast": 0e0,
    "syntaxcheck": 0e0,
    "moar": 0e0,
    "start": 0e0,
    "parse": 4.124e0,
    "mast": 0.004e0,
    "mbc": 0.001e0
  },
  "GTK::Raw::Spinner": {
    "syntaxcheck": 0e0,
    "optimize": 0.001e0,
    "ast": 0e0,
    "mast": 0.003e0,
    "mbc": 0.001e0,
    "moar": 0e0,
    "start": 0e0,
    "parse": 2.917e0
  },
  "GTK::FileChooserButton": {
    "mast": 0.003e0,
    "mbc": 0.001e0,
    "parse": 4.106e0,
    "start": 0e0,
    "moar": 0e0,
    "syntaxcheck": 0e0,
    "ast": 0e0,
    "optimize": 0.001e0
  },
  "GTK::CellAreaBox": {
    "mbc": 0.001e0,
    "mast": 0.008e0,
    "moar": 0e0,
    "parse": 4.063e0,
    "start": 0e0,
    "syntaxcheck": 0e0,
    "ast": 0e0,
    "optimize": 0.002e0
  },
  "GTK::Roles::AppChooser": {
    "syntaxcheck": 0e0,
    "optimize": 0.001e0,
    "ast": 0e0,
    "mbc": 0e0,
    "mast": 0.003e0,
    "parse": 2.698e0,
    "start": 0e0,
    "moar": 0e0
  },
  "GTK::Raw::Switch": {
    "parse": 3.037e0,
    "start": 0e0,
    "moar": 0e0,
    "mbc": 0.001e0,
    "mast": 0.005e0,
    "optimize": 0.001e0,
    "ast": 0e0,
    "syntaxcheck": 0e0
  },
  "GTK::Compat::Screen": {
    "ast": 0e0,
    "optimize": 0.001e0,
    "syntaxcheck": 0e0,
    "parse": 3.287e0,
    "start": 0e0,
    "moar": 0e0,
    "mast": 0.003e0,
    "mbc": 0.001e0
  },
  "GTK::Compat::Display": {
    "parse": 3.321e0,
    "start": 0e0,
    "moar": 0e0,
    "mbc": 0.001e0,
    "mast": 0.003e0,
    "ast": 0e0,
    "optimize": 0.001e0,
    "syntaxcheck": 0e0
  },
  "GTK::Compat::Raw::AppLaunchContext": {
    "optimize": 0.002e0,
    "ast": 0e0,
    "syntaxcheck": 0e0,
    "start": 0e0,
    "parse": 2.708e0,
    "moar": 0e0,
    "mast": 0.008e0,
    "mbc": 0.001e0
  },
  "Pango::FontDescription": {
    "syntaxcheck": 0e0,
    "optimize": 0.001e0,
    "ast": 0e0,
    "mast": 0.009e0,
    "mbc": 0.001e0,
    "moar": 0e0,
    "parse": 3.008e0,
    "start": 0e0
  },
  "GTK::Compat::Roles::Signals::Window": {
    "ast": 0e0,
    "optimize": 0.001e0,
    "syntaxcheck": 0e0,
    "parse": 3.375e0,
    "start": 0e0,
    "moar": 0e0,
    "mast": 0.003e0,
    "mbc": 0.001e0
  },
  "GTK::Compat::Roles::ListData": {
    "mbc": 0.001e0,
    "mast": 0.008e0,
    "start": 0e0,
    "parse": 2.606e0,
    "moar": 0e0,
    "syntaxcheck": 0e0,
    "optimize": 0.002e0,
    "ast": 0e0
  },
  "GTK::Raw::TreeModel": {
    "ast": 0e0,
    "optimize": 0.002e0,
    "syntaxcheck": 0e0,
    "moar": 0e0,
    "start": 0e0,
    "parse": 6.559e0,
    "mbc": 0.001e0,
    "mast": 0.004e0
  },
  "GTK::CellRenderer": {
    "moar": 0e0,
    "parse": 3.633e0,
    "start": 0e0,
    "mast": 0.003e0,
    "mbc": 0.001e0,
    "optimize": 0.001e0,
    "ast": 0e0,
    "syntaxcheck": 0e0
  },
  "GTK::Window": {
    "ast": 0e0,
    "optimize": 0.001e0,
    "syntaxcheck": 0e0,
    "start": 0e0,
    "parse": 5.335e0,
    "moar": 0e0,
    "mast": 0.003e0,
    "mbc": 0.001e0
  },
  "GTK::CellRendererCombo": {
    "ast": 0e0,
    "optimize": 0.001e0,
    "syntaxcheck": 0e0,
    "moar": 0e0,
    "parse": 4.207e0,
    "start": 0e0,
    "mast": 0.003e0,
    "mbc": 0.001e0
  },
  "GTK::Builder::ListBoxRow": {
    "syntaxcheck": 0e0,
    "ast": 0e0,
    "optimize": 0.002e0,
    "mast": 0.008e0,
    "mbc": 0.001e0,
    "start": 0e0,
    "parse": 2.097e0,
    "moar": 0e0
  },
  "GTK::Button": {
    "parse": 4.279e0,
    "start": 0e0,
    "moar": 0e0,
    "mbc": 0.001e0,
    "mast": 0.003e0,
    "optimize": 0.001e0,
    "ast": 0e0,
    "syntaxcheck": 0e0
  },
  "GTK::Raw::Stack": {
    "moar": 0e0,
    "start": 0e0,
    "parse": 4.415e0,
    "mast": 0.004e0,
    "mbc": 0.001e0,
    "ast": 0e0,
    "optimize": 0.001e0,
    "syntaxcheck": 0e0
  },
  "GTK::Raw::TextTag": {
    "moar": 0e0,
    "parse": 3.032e0,
    "start": 0e0,
    "mbc": 0.001e0,
    "mast": 0.003e0,
    "optimize": 0.001e0,
    "ast": 0e0,
    "syntaxcheck": 0e0
  },
  "GTK::Raw::AspectFrame": {
    "syntaxcheck": 0e0,
    "ast": 0e0,
    "optimize": 0.002e0,
    "mbc": 0.001e0,
    "mast": 0.007e0,
    "start": 0e0,
    "parse": 2.747e0,
    "moar": 0e0
  },
  "GTK::Box": {
    "syntaxcheck": 0e0,
    "optimize": 0.001e0,
    "ast": 0e0,
    "mast": 0.003e0,
    "mbc": 0e0,
    "moar": 0e0,
    "start": 0e0,
    "parse": 4.348e0
  },
  "GTK::Compat::VariantIter": {
    "mbc": 0.001e0,
    "mast": 0.013e0,
    "moar": 0e0,
    "parse": 2.551e0,
    "start": 0e0,
    "syntaxcheck": 0e0,
    "ast": 0e0,
    "optimize": 0.002e0
  },
  "GTK::Raw::ToolItem": {
    "mbc": 0.001e0,
    "mast": 0.003e0,
    "parse": 5.071e0,
    "start": 0e0,
    "moar": 0e0,
    "syntaxcheck": 0e0,
    "optimize": 0.001e0,
    "ast": 0e0
  },
  "GTK::ProgressBar": {
    "mbc": 0.001e0,
    "mast": 0.003e0,
    "parse": 3.91e0,
    "start": 0e0,
    "moar": 0e0,
    "syntaxcheck": 0e0,
    "ast": 0e0,
    "optimize": 0.001e0
  },
  "GTK::Raw::CheckMenuItem": {
    "mbc": 0.001e0,
    "mast": 0.003e0,
    "start": 0e0,
    "parse": 3.326e0,
    "moar": 0e0,
    "syntaxcheck": 0e0,
    "ast": 0e0,
    "optimize": 0.001e0
  },
  "GTK::Raw::Toolbar": {
    "syntaxcheck": 0e0,
    "ast": 0e0,
    "optimize": 0.001e0,
    "mast": 0.003e0,
    "mbc": 0.001e0,
    "start": 0e0,
    "parse": 3.617e0,
    "moar": 0e0
  },
  "GTK::TextChildAnchor": {
    "optimize": 0.002e0,
    "ast": 0e0,
    "syntaxcheck": 0e0,
    "moar": 0e0,
    "parse": 2.636e0,
    "start": 0e0,
    "mast": 0.008e0,
    "mbc": 0.001e0
  },
  "GTK::FlowBoxChild": {
    "optimize": 0.001e0,
    "ast": 0e0,
    "syntaxcheck": 0e0,
    "start": 0e0,
    "parse": 3.885e0,
    "moar": 0e0,
    "mbc": 0e0,
    "mast": 0.003e0
  },
  "GTK::Raw::ButtonBox": {
    "mbc": 0.001e0,
    "mast": 0.003e0,
    "moar": 0e0,
    "parse": 3.239e0,
    "start": 0e0,
    "syntaxcheck": 0e0,
    "optimize": 0.001e0,
    "ast": 0e0
  },
  "GTK::Raw::Container": {
    "mast": 0.004e0,
    "mbc": 0.001e0,
    "moar": 0e0,
    "parse": 5.751e0,
    "start": 0e0,
    "syntaxcheck": 0e0,
    "optimize": 0.001e0,
    "ast": 0e0
  },
  "GTK::Raw::TextChildAnchor": {
    "mast": 0.007e0,
    "mbc": 0.001e0,
    "moar": 0e0,
    "start": 0e0,
    "parse": 2.817e0,
    "syntaxcheck": 0e0,
    "optimize": 0.002e0,
    "ast": 0e0
  },
  "GTK::Raw::ComboBoxText": {
    "moar": 0e0,
    "start": 0e0,
    "parse": 3.489e0,
    "mast": 0.003e0,
    "mbc": 0.001e0,
    "optimize": 0.001e0,
    "ast": 0e0,
    "syntaxcheck": 0e0
  },
  "GTK::Compat::Raw::FrameClock": {
    "syntaxcheck": 0e0,
    "optimize": 0.001e0,
    "ast": 0e0,
    "mbc": 0.001e0,
    "mast": 0.003e0,
    "moar": 0e0,
    "start": 0e0,
    "parse": 3.305e0
  },
  "Data::Dump::Tree": {
    "moar": 0e0,
    "start": 0e0,
    "parse": 6.385e0,
    "mast": 0.003e0,
    "mbc": 0.001e0,
    "optimize": 0.001e0,
    "ast": 0e0,
    "syntaxcheck": 0e0
  },
  "GTK::Raw::LockButton": {
    "start": 0e0,
    "parse": 2.911e0,
    "moar": 0e0,
    "mast": 0.003e0,
    "mbc": 0.001e0,
    "optimize": 0.001e0,
    "ast": 0e0,
    "syntaxcheck": 0e0
  },
  "GTK::Builder::Image": {
    "parse": 2.242e0,
    "start": 0e0,
    "moar": 0e0,
    "mbc": 0.001e0,
    "mast": 0.008e0,
    "optimize": 0.002e0,
    "ast": 0e0,
    "syntaxcheck": 0e0
  },
  "GTK::Raw::Notebook": {
    "mast": 0.004e0,
    "mbc": 0.001e0,
    "moar": 0e0,
    "parse": 5.928e0,
    "start": 0e0,
    "syntaxcheck": 0e0,
    "optimize": 0.002e0,
    "ast": 0e0
  },
  "GTK::Roles::Signals::Toolbar": {
    "moar": 0e0,
    "start": 0e0,
    "parse": 2.964e0,
    "mast": 0.007e0,
    "mbc": 0.001e0,
    "optimize": 0.002e0,
    "ast": 0e0,
    "syntaxcheck": 0e0
  },
  "GTK::Widget": {
    "mast": 0.003e0,
    "mbc": 0.001e0,
    "moar": 0e0,
    "parse": 7.855e0,
    "start": 0e0,
    "syntaxcheck": 0e0,
    "ast": 0e0,
    "optimize": 0.001e0
  },
  "GTK::Raw::Button": {
    "optimize": 0.001e0,
    "ast": 0e0,
    "syntaxcheck": 0e0,
    "moar": 0e0,
    "parse": 4.549e0,
    "start": 0e0,
    "mbc": 0.001e0,
    "mast": 0.007e0
  },
  "GTK::Compat::Array": {
    "moar": 0e0,
    "parse": 2.607e0,
    "start": 0e0,
    "mast": 0.008e0,
    "mbc": 0.001e0,
    "ast": 0e0,
    "optimize": 0.002e0,
    "syntaxcheck": 0e0
  },
  "GTK::Roles::TreeModel": {
    "syntaxcheck": 0e0,
    "optimize": 0.001e0,
    "ast": 0e0,
    "mbc": 0.001e0,
    "mast": 0.003e0,
    "moar": 0e0,
    "parse": 3.404e0,
    "start": 0e0
  },
  "GTK::Roles::LatchedContents": {
    "syntaxcheck": 0e0,
    "optimize": 0.001e0,
    "ast": 0e0,
    "mast": 0.003e0,
    "mbc": 0.001e0,
    "start": 0e0,
    "parse": 3.757e0,
    "moar": 0e0
  },
  "GTK::Raw::HeaderBar": {
    "mbc": 0.001e0,
    "mast": 0.003e0,
    "start": 0e0,
    "parse": 3.778e0,
    "moar": 0e0,
    "syntaxcheck": 0e0,
    "ast": 0e0,
    "optimize": 0.001e0
  },
  "GTK::Raw::ReturnedValue": {
    "syntaxcheck": 0e0,
    "optimize": 0.002e0,
    "ast": 0e0,
    "mast": 0.007e0,
    "mbc": 0.001e0,
    "moar": 0e0,
    "parse": 0.92e0,
    "start": 0e0
  },
  "GTK::Raw::Scrollable": {
    "ast": 0e0,
    "optimize": 0.001e0,
    "syntaxcheck": 0e0,
    "moar": 0e0,
    "start": 0e0,
    "parse": 3.356e0,
    "mbc": 0.001e0,
    "mast": 0.003e0
  },
  "GTK::Render": {
    "syntaxcheck": 0e0,
    "ast": 0e0,
    "optimize": 0.001e0,
    "mbc": 0e0,
    "mast": 0.003e0,
    "moar": 0e0,
    "parse": 3.18e0,
    "start": 0e0
  },
  "GTK::Raw::SpinButton": {
    "syntaxcheck": 0e0,
    "optimize": 0.001e0,
    "ast": 0e0,
    "mast": 0.005e0,
    "mbc": 0.001e0,
    "moar": 0e0,
    "parse": 4.353e0,
    "start": 0e0
  },
  "GTK::Scale": {
    "mast": 0.003e0,
    "mbc": 0.001e0,
    "moar": 0e0,
    "parse": 4.259e0,
    "start": 0e0,
    "syntaxcheck": 0e0,
    "ast": 0e0,
    "optimize": 0.001e0
  },
  "GTK::ToolItem": {
    "moar": 0e0,
    "start": 0e0,
    "parse": 4.923e0,
    "mbc": 0.001e0,
    "mast": 0.003e0,
    "ast": 0e0,
    "optimize": 0.001e0,
    "syntaxcheck": 0e0
  },
  "GTK::Raw::ToolButton": {
    "optimize": 0.001e0,
    "ast": 0e0,
    "syntaxcheck": 0e0,
    "start": 0e0,
    "parse": 3.582e0,
    "moar": 0e0,
    "mbc": 0.001e0,
    "mast": 0.004e0
  },
  "GTK::Compat::GList": {
    "ast": 0e0,
    "optimize": 0.002e0,
    "syntaxcheck": 0e0,
    "moar": 0e0,
    "start": 0e0,
    "parse": 2.96e0,
    "mbc": 0.001e0,
    "mast": 0.013e0
  },
  "GTK::Raw::EventBox": {
    "mast": 0.003e0,
    "mbc": 0.001e0,
    "start": 0e0,
    "parse": 2.971e0,
    "moar": 0e0,
    "syntaxcheck": 0e0,
    "ast": 0e0,
    "optimize": 0.001e0
  },
  "GTK::Raw::ComboBox": {
    "syntaxcheck": 0e0,
    "optimize": 0.002e0,
    "ast": 0e0,
    "mast": 0.004e0,
    "mbc": 0.001e0,
    "parse": 5.601e0,
    "start": 0e0,
    "moar": 0e0
  },
  "GTK::Compat::Roles::Object": {
    "parse": 2.556e0,
    "start": 0e0,
    "moar": 0e0,
    "mast": 0.003e0,
    "mbc": 0.001e0,
    "optimize": 0.001e0,
    "ast": 0e0,
    "syntaxcheck": 0e0
  },
  "GTK::Compat::Selection": {
    "ast": 0e0,
    "optimize": 0.002e0,
    "syntaxcheck": 0e0,
    "moar": 0e0,
    "parse": 2.652e0,
    "start": 0e0,
    "mbc": 0.001e0,
    "mast": 0.008e0
  },
  "GTK::Raw::ProgressBar": {
    "moar": 0e0,
    "start": 0e0,
    "parse": 3.633e0,
    "mast": 0.003e0,
    "mbc": 0.001e0,
    "optimize": 0.001e0,
    "ast": 0e0,
    "syntaxcheck": 0e0
  },
  "GTK::Raw::DragSource": {
    "optimize": 0.001e0,
    "ast": 0e0,
    "syntaxcheck": 0e0,
    "start": 0e0,
    "parse": 3.434e0,
    "moar": 0e0,
    "mbc": 0.001e0,
    "mast": 0.003e0
  },
  "GTK::ToolPalette": {
    "ast": 0e0,
    "optimize": 0.001e0,
    "syntaxcheck": 0e0,
    "moar": 0e0,
    "start": 0e0,
    "parse": 4.58e0,
    "mbc": 0.001e0,
    "mast": 0.003e0
  },
  "GTK::Raw::CellAreaContext": {
    "mbc": 0.001e0,
    "mast": 0.008e0,
    "parse": 3.323e0,
    "start": 0e0,
    "moar": 0e0,
    "syntaxcheck": 0e0,
    "ast": 0e0,
    "optimize": 0.002e0
  },
  "GTK::Roles::Types": {
    "optimize": 0.001e0,
    "ast": 0e0,
    "syntaxcheck": 0e0,
    "start": 0e0,
    "parse": 2.727e0,
    "moar": 0e0,
    "mbc": 0.001e0,
    "mast": 0.003e0
  },
  "GTK::Raw::RadioToolButton": {
    "syntaxcheck": 0e0,
    "optimize": 0.001e0,
    "ast": 0e0,
    "mast": 0.003e0,
    "mbc": 0.001e0,
    "moar": 0e0,
    "parse": 3.101e0,
    "start": 0e0
  },
  "GTK::PrintJob": {
    "ast": 0e0,
    "optimize": 0.002e0,
    "syntaxcheck": 0e0,
    "parse": 3.327e0,
    "start": 0e0,
    "moar": 0e0,
    "mbc": 0.001e0,
    "mast": 0.008e0
  },
  "GTK::Compat::Device": {
    "ast": 0e0,
    "optimize": 0.002e0,
    "syntaxcheck": 0e0,
    "start": 0e0,
    "parse": 3.594e0,
    "moar": 0e0,
    "mast": 0.013e0,
    "mbc": 0.001e0
  },
  "GTK::Dialog::Raw::PrintUnix": {
    "start": 0e0,
    "parse": 3.909e0,
    "moar": 0e0,
    "mast": 0.008e0,
    "mbc": 0.001e0,
    "ast": 0e0,
    "optimize": 0.002e0,
    "syntaxcheck": 0e0
  },
  "GTK::Builder::Revealer": {
    "optimize": 0.002e0,
    "ast": 0e0,
    "syntaxcheck": 0e0,
    "start": 0e0,
    "parse": 2.247e0,
    "moar": 0e0,
    "mast": 0.008e0,
    "mbc": 0.001e0
  },
  "Cairo": {
    "start": 0e0,
    "parse": 13.164e0,
    "moar": 0e0,
    "mast": 0.008e0,
    "mbc": 0.003e0,
    "optimize": 0.005e0,
    "ast": 0e0,
    "syntaxcheck": 0e0
  },
  "GTK::Compat::Monitor": {
    "syntaxcheck": 0e0,
    "ast": 0e0,
    "optimize": 0.002e0,
    "mast": 0.008e0,
    "mbc": 0.001e0,
    "start": 0e0,
    "parse": 3.093e0,
    "moar": 0e0
  },
  "GTK::SearchEntry": {
    "parse": 3.972e0,
    "start": 0e0,
    "moar": 0e0,
    "mast": 0.004e0,
    "mbc": 0.001e0,
    "ast": 0e0,
    "optimize": 0.001e0,
    "syntaxcheck": 0e0
  },
  "GTK::Raw::AccelGroup": {
    "optimize": 0.001e0,
    "ast": 0e0,
    "syntaxcheck": 0e0,
    "start": 0e0,
    "parse": 4.449e0,
    "moar": 0e0,
    "mbc": 0.001e0,
    "mast": 0.004e0
  },
  "GTK::Spinner": {
    "syntaxcheck": 0e0,
    "optimize": 0.001e0,
    "ast": 0e0,
    "mast": 0.003e0,
    "mbc": 0.001e0,
    "start": 0e0,
    "parse": 4.141e0,
    "moar": 0e0
  },
  "GTK::Compat::VariantDict": {
    "optimize": 0.002e0,
    "ast": 0e0,
    "syntaxcheck": 0e0,
    "moar": 0e0,
    "parse": 2.618e0,
    "start": 0e0,
    "mbc": 0.001e0,
    "mast": 0.008e0
  },
  "GTK::Compat::GSList": {
    "moar": 0e0,
    "start": 0e0,
    "parse": 2.958e0,
    "mast": 0.003e0,
    "mbc": 0.001e0,
    "ast": 0e0,
    "optimize": 0.001e0,
    "syntaxcheck": 0e0
  },
  "GTK::Raw::RadioButton": {
    "ast": 0e0,
    "optimize": 0.001e0,
    "syntaxcheck": 0e0,
    "moar": 0e0,
    "parse": 3.33e0,
    "start": 0e0,
    "mbc": 0.001e0,
    "mast": 0.003e0
  },
  "GTK::Raw::TreeDnD": {
    "start": 0e0,
    "parse": 3.243e0,
    "moar": 0e0,
    "mbc": 0.001e0,
    "mast": 0.003e0,
    "optimize": 0.001e0,
    "ast": 0e0,
    "syntaxcheck": 0e0
  },
  "GTK::Raw::TreeView": {
    "syntaxcheck": 0e0,
    "ast": 0e0,
    "optimize": 0.003e0,
    "mbc": 0.001e0,
    "mast": 0.005e0,
    "moar": 0e0,
    "start": 0e0,
    "parse": 9.72e0
  },
  "GTK::Printer": {
    "start": 0e0,
    "parse": 3.135e0,
    "moar": 0e0,
    "mbc": 0.001e0,
    "mast": 0.007e0,
    "optimize": 0.002e0,
    "ast": 0e0,
    "syntaxcheck": 0e0
  },
  "GTK::TargetEntry": {
    "syntaxcheck": 0e0,
    "ast": 0e0,
    "optimize": 0.001e0,
    "mbc": 0e0,
    "mast": 0.003e0,
    "moar": 0e0,
    "start": 0e0,
    "parse": 2.835e0
  },
  "GTK::Expander": {
    "mast": 0.003e0,
    "mbc": 0.001e0,
    "start": 0e0,
    "parse": 4.179e0,
    "moar": 0e0,
    "syntaxcheck": 0e0,
    "optimize": 0.001e0,
    "ast": 0e0
  },
  "GTK::Compat::Binding": {
    "syntaxcheck": 0e0,
    "optimize": 0.002e0,
    "ast": 0e0,
    "mast": 0.008e0,
    "mbc": 0.001e0,
    "start": 0e0,
    "parse": 2.603e0,
    "moar": 0e0
  },
  "GTK::ComboBoxText": {
    "syntaxcheck": 0e0,
    "ast": 0e0,
    "optimize": 0.001e0,
    "mast": 0.003e0,
    "mbc": 0.001e0,
    "moar": 0e0,
    "parse": 4.195e0,
    "start": 0e0
  },
  "GTK::TreeIter": {
    "syntaxcheck": 0e0,
    "ast": 0e0,
    "optimize": 0.001e0,
    "mbc": 0.001e0,
    "mast": 0.003e0,
    "moar": 0e0,
    "parse": 2.665e0,
    "start": 0e0
  },
  "GTK::Compat::Settings": {
    "moar": 0e0,
    "start": 0e0,
    "parse": 3.13e0,
    "mbc": 0.001e0,
    "mast": 0.007e0,
    "optimize": 0.002e0,
    "ast": 0e0,
    "syntaxcheck": 0e0
  },
  "GTK::CellRendererAccel": {
    "ast": 0e0,
    "optimize": 0.002e0,
    "syntaxcheck": 0e0,
    "moar": 0e0,
    "parse": 2.999e0,
    "start": 0e0,
    "mbc": 0.001e0,
    "mast": 0.008e0
  },
  "GTK::Compat::Raw::Pixbuf::Transforms": {
    "syntaxcheck": 0e0,
    "optimize": 0.001e0,
    "ast": 0e0,
    "mbc": 0.001e0,
    "mast": 0.003e0,
    "parse": 2.95e0,
    "start": 0e0,
    "moar": 0e0
  },
  "GTK::AppButton": {
    "mbc": 0.001e0,
    "mast": 0.003e0,
    "moar": 0e0,
    "start": 0e0,
    "parse": 4.364e0,
    "syntaxcheck": 0e0,
    "optimize": 0.001e0,
    "ast": 0e0
  },
  "GTK::Settings": {
    "mbc": 0.001e0,
    "mast": 0.007e0,
    "start": 0e0,
    "parse": 4.755e0,
    "moar": 0e0,
    "syntaxcheck": 0e0,
    "ast": 0e0,
    "optimize": 0.002e0
  },
  "GTK::Compat::Cursor": {
    "ast": 0e0,
    "optimize": 0.001e0,
    "syntaxcheck": 0e0,
    "start": 0e0,
    "parse": 3.084e0,
    "moar": 0e0,
    "mbc": 0.001e0,
    "mast": 0.003e0
  },
  "GTK::Raw::SizeGroup": {
    "optimize": 0.001e0,
    "ast": 0e0,
    "syntaxcheck": 0e0,
    "moar": 0e0,
    "parse": 3.255e0,
    "start": 0e0,
    "mast": 0.003e0,
    "mbc": 0.001e0
  },
  "GTK::Raw::DragDest": {
    "optimize": 0.001e0,
    "ast": 0e0,
    "syntaxcheck": 0e0,
    "parse": 3.356e0,
    "start": 0e0,
    "moar": 0e0,
    "mbc": 0.001e0,
    "mast": 0.003e0
  },
  "GTK::ToggleToolButton": {
    "ast": 0e0,
    "optimize": 0.001e0,
    "syntaxcheck": 0e0,
    "moar": 0e0,
    "start": 0e0,
    "parse": 4.088e0,
    "mast": 0.003e0,
    "mbc": 0.001e0
  },
  "GTK::ScrolledWindow": {
    "optimize": 0.001e0,
    "ast": 0e0,
    "syntaxcheck": 0e0,
    "moar": 0e0,
    "parse": 4.69e0,
    "start": 0e0,
    "mbc": 0.001e0,
    "mast": 0.029e0
  },
  "GTK::Compat::Raw::Device": {
    "ast": 0e0,
    "optimize": 0.002e0,
    "syntaxcheck": 0e0,
    "moar": 0e0,
    "parse": 4.374e0,
    "start": 0e0,
    "mast": 0.009e0,
    "mbc": 0.002e0
  },
  "GTK::Raw::Places": {
    "ast": 0e0,
    "optimize": 0.001e0,
    "syntaxcheck": 0e0,
    "parse": 4.577e0,
    "start": 0e0,
    "moar": 0e0,
    "mbc": 0.001e0,
    "mast": 0.004e0
  },
  "GTK::Raw::Scale": {
    "mbc": 0.001e0,
    "mast": 0.003e0,
    "start": 0e0,
    "parse": 3.796e0,
    "moar": 0e0,
    "syntaxcheck": 0e0,
    "ast": 0e0,
    "optimize": 0.001e0
  },
  "GTK::Roles::Signals::TextView": {
    "optimize": 0.001e0,
    "ast": 0e0,
    "syntaxcheck": 0e0,
    "moar": 0e0,
    "start": 0e0,
    "parse": 3.057e0,
    "mast": 0.003e0,
    "mbc": 0.001e0
  },
  "GTK::Raw::VolumeButton": {
    "optimize": 0.001e0,
    "ast": 0e0,
    "syntaxcheck": 0e0,
    "moar": 0e0,
    "parse": 2.832e0,
    "start": 0e0,
    "mbc": 0.001e0,
    "mast": 0.003e0
  },
  "GTK::Builder::Menu": {
    "parse": 2.188e0,
    "start": 0e0,
    "moar": 0e0,
    "mast": 0.008e0,
    "mbc": 0.001e0,
    "ast": 0e0,
    "optimize": 0.002e0,
    "syntaxcheck": 0e0
  },
  "Pango::Layout": {
    "syntaxcheck": 0e0,
    "optimize": 0.001e0,
    "ast": 0e0,
    "mast": 0.003e0,
    "mbc": 0.001e0,
    "start": 0e0,
    "parse": 12.25e0,
    "moar": 0e0
  },
  "GTK::Raw::Assistant": {
    "syntaxcheck": 0e0,
    "ast": 0e0,
    "optimize": 0.001e0,
    "mbc": 0.001e0,
    "mast": 0.004e0,
    "start": 0e0,
    "parse": 4.741e0,
    "moar": 0e0
  },
  "GTK::ToolButton": {
    "mbc": 0.001e0,
    "mast": 0.003e0,
    "start": 0e0,
    "parse": 4.337e0,
    "moar": 0e0,
    "syntaxcheck": 0e0,
    "ast": 0e0,
    "optimize": 0.001e0
  },
  "GTK::Builder::Box": {
    "ast": 0e0,
    "optimize": 0.002e0,
    "syntaxcheck": 0e0,
    "moar": 0e0,
    "parse": 2.301e0,
    "start": 0e0,
    "mast": 0.008e0,
    "mbc": 0.001e0
  },
  "GTK::Roles::Signals::EntryCompletion": {
    "syntaxcheck": 0e0,
    "ast": 0e0,
    "optimize": 0.002e0,
    "mast": 0.007e0,
    "mbc": 0.001e0,
    "parse": 2.795e0,
    "start": 0e0,
    "moar": 0e0
  },
  "GTK::Raw::Separator": {
    "optimize": 0.001e0,
    "ast": 0e0,
    "syntaxcheck": 0e0,
    "moar": 0e0,
    "start": 0e0,
    "parse": 2.797e0,
    "mbc": 0e0,
    "mast": 0.003e0
  },
  "GTK::Pane": {
    "syntaxcheck": 0e0,
    "optimize": 0.002e0,
    "ast": 0e0,
    "mast": 0.006e0,
    "mbc": 0.001e0,
    "moar": 0e0,
    "parse": 4.339e0,
    "start": 0e0
  },
  "GTK::Roles::Signals::TextTagTable": {
    "syntaxcheck": 0e0,
    "ast": 0e0,
    "optimize": 0.001e0,
    "mbc": 0e0,
    "mast": 0.003e0,
    "moar": 0e0,
    "start": 0e0,
    "parse": 3.222e0
  },
  "GTK::Raw::TextTagTable": {
    "ast": 0e0,
    "optimize": 0.001e0,
    "syntaxcheck": 0e0,
    "moar": 0e0,
    "parse": 3.093e0,
    "start": 0e0,
    "mbc": 0.001e0,
    "mast": 0.003e0
  },
  "GTK::PrintSettings": {
    "ast": 0e0,
    "optimize": 0.001e0,
    "syntaxcheck": 0e0,
    "parse": 3.777e0,
    "start": 0e0,
    "moar": 0e0,
    "mbc": 0.001e0,
    "mast": 0.003e0
  },
  "GTK::CellRendererText": {
    "parse": 4.553e0,
    "start": 0e0,
    "moar": 0e0,
    "mbc": 0.001e0,
    "mast": 0.003e0,
    "optimize": 0.001e0,
    "ast": 0e0,
    "syntaxcheck": 0e0
  },
  "GTK::Viewport": {
    "start": 0e0,
    "parse": 4.164e0,
    "moar": 0e0,
    "mbc": 0.001e0,
    "mast": 0.013e0,
    "ast": 0e0,
    "optimize": 0.002e0,
    "syntaxcheck": 0e0
  },
  "GTK::Raw::CellRendererSpinner": {
    "ast": 0e0,
    "optimize": 0.002e0,
    "syntaxcheck": 0e0,
    "parse": 2.64e0,
    "start": 0e0,
    "moar": 0e0,
    "mast": 0.014e0,
    "mbc": 0.001e0
  },
  "GTK::Raw::CellEditable": {
    "ast": 0e0,
    "optimize": 0.001e0,
    "syntaxcheck": 0e0,
    "parse": 2.83e0,
    "start": 0e0,
    "moar": 0e0,
    "mast": 0.003e0,
    "mbc": 0.001e0
  },
  "GTK::TreeModelSort": {
    "syntaxcheck": 0e0,
    "optimize": 0.002e0,
    "ast": 0e0,
    "mbc": 0.001e0,
    "mast": 0.008e0,
    "start": 0e0,
    "parse": 2.88e0,
    "moar": 0e0
  },
  "GTK::Roles::ColorChooser": {
    "parse": 2.876e0,
    "start": 0e0,
    "moar": 0e0,
    "mbc": 0.001e0,
    "mast": 0.009e0,
    "ast": 0e0,
    "optimize": 0.001e0,
    "syntaxcheck": 0e0
  },
  "GTK::RadioToolButton": {
    "optimize": 0.001e0,
    "ast": 0e0,
    "syntaxcheck": 0e0,
    "moar": 0e0,
    "parse": 4.402e0,
    "start": 0e0,
    "mbc": 0.001e0,
    "mast": 0.003e0
  },
  "GTK::Raw::StackSidebar": {
    "ast": 0e0,
    "optimize": 0.002e0,
    "syntaxcheck": 0e0,
    "moar": 0e0,
    "start": 0e0,
    "parse": 2.937e0,
    "mast": 0.003e0,
    "mbc": 0.001e0
  },
  "GTK::TreeView": {
    "optimize": 0.021e0,
    "ast": 0e0,
    "syntaxcheck": 0e0,
    "moar": 0e0,
    "parse": 6.6e0,
    "start": 0e0,
    "mbc": 0.014e0,
    "mast": 0.049e0
  },
  "GTK::Compat::Rectangle": {
    "optimize": 0.001e0,
    "ast": 0e0,
    "syntaxcheck": 0e0,
    "moar": 0e0,
    "start": 0e0,
    "parse": 2.617e0,
    "mbc": 0.001e0,
    "mast": 0.003e0
  },
  "GTK::Dialog::PrintUnix": {
    "start": 0e0,
    "parse": 4.215e0,
    "moar": 0e0,
    "mbc": 0.001e0,
    "mast": 0.02e0,
    "optimize": 0.002e0,
    "ast": 0e0,
    "syntaxcheck": 0e0
  },
  "GTK::Compat::Types": {
    "parse": 7.05e0,
    "start": 0e0,
    "moar": 0e0,
    "mbc": 0.014e0,
    "mast": 0.028e0,
    "optimize": 0.012e0,
    "ast": 0e0,
    "syntaxcheck": 0e0
  },
  "GTK::Grid": {
    "parse": 4.532e0,
    "start": 0e0,
    "moar": 0e0,
    "mbc": 0.001e0,
    "mast": 0.003e0,
    "optimize": 0.001e0,
    "ast": 0e0,
    "syntaxcheck": 0e0
  },
  "GTK::Raw::ScrolledWindow": {
    "mast": 0.004e0,
    "mbc": 0.001e0,
    "parse": 4.91e0,
    "start": 0e0,
    "moar": 0e0,
    "syntaxcheck": 0e0,
    "optimize": 0.001e0,
    "ast": 0e0
  },
  "GTK::AccelGroup": {
    "mast": 0.003e0,
    "mbc": 0.001e0,
    "start": 0e0,
    "parse": 3.03e0,
    "moar": 0e0,
    "syntaxcheck": 0e0,
    "ast": 0e0,
    "optimize": 0.008e0
  },
  "GTK::Raw::StyleContext": {
    "ast": 0e0,
    "optimize": 0.002e0,
    "syntaxcheck": 0e0,
    "parse": 7.017e0,
    "start": 0e0,
    "moar": 0e0,
    "mbc": 0.001e0,
    "mast": 0.005e0
  },
  "GTK::PrintContext": {
    "mast": 0.003e0,
    "mbc": 0.001e0,
    "start": 0e0,
    "parse": 3.337e0,
    "moar": 0e0,
    "syntaxcheck": 0e0,
    "optimize": 0.001e0,
    "ast": 0e0
  },
  "GTK::Raw::Statusbar": {
    "syntaxcheck": 0e0,
    "ast": 0e0,
    "optimize": 0.001e0,
    "mast": 0.003e0,
    "mbc": 0.001e0,
    "parse": 3.165e0,
    "start": 0e0,
    "moar": 0e0
  },
  "GTK::Compat::Raw::Variant": {
    "ast": 0e0,
    "optimize": 0.003e0,
    "syntaxcheck": 0e0,
    "parse": 7.453e0,
    "start": 0e0,
    "moar": 0e0,
    "mast": 0.009e0,
    "mbc": 0.003e0
  },
  "GTK::MenuItem": {
    "syntaxcheck": 0e0,
    "optimize": 0.001e0,
    "ast": 0e0,
    "mast": 0.003e0,
    "mbc": 0.001e0,
    "moar": 0e0,
    "start": 0e0,
    "parse": 4.214e0
  },
  "GTK::Compat::RGBA": {
    "moar": 0e0,
    "parse": 3.016e0,
    "start": 0e0,
    "mbc": 0.001e0,
    "mast": 0.003e0,
    "optimize": 0.001e0,
    "ast": 0e0,
    "syntaxcheck": 0e0
  },
  "GTK::Roles::Orientable": {
    "syntaxcheck": 0e0,
    "ast": 0e0,
    "optimize": 0.001e0,
    "mast": 0.003e0,
    "mbc": 0e0,
    "moar": 0e0,
    "parse": 2.713e0,
    "start": 0e0
  },
  "GTK::Raw::Label": {
    "mast": 0.004e0,
    "mbc": 0.001e0,
    "moar": 0e0,
    "parse": 6.403e0,
    "start": 0e0,
    "syntaxcheck": 0e0,
    "optimize": 0.002e0,
    "ast": 0e0
  },
  "GTK::Compat::Raw::Selection": {
    "syntaxcheck": 0e0,
    "ast": 0e0,
    "optimize": 0.002e0,
    "mbc": 0.001e0,
    "mast": 0.008e0,
    "parse": 2.85e0,
    "start": 0e0,
    "moar": 0e0
  },
  "GTK::Builder": {
    "ast": 0e0,
    "optimize": 0.001e0,
    "syntaxcheck": 0e0,
    "start": 0e0,
    "parse": 9.815e0,
    "moar": 0e0,
    "mbc": 0.001e0,
    "mast": 0.003e0
  },
  "GTK::Toolbar": {
    "moar": 0e0,
    "start": 0e0,
    "parse": 4.446e0,
    "mast": 0.003e0,
    "mbc": 0.001e0,
    "optimize": 0.001e0,
    "ast": 0e0,
    "syntaxcheck": 0e0
  },
  "GTK::StackSwitcher": {
    "optimize": 0.001e0,
    "ast": 0e0,
    "syntaxcheck": 0e0,
    "start": 0e0,
    "parse": 3.878e0,
    "moar": 0e0,
    "mbc": 0.001e0,
    "mast": 0.003e0
  },
  "GTK::Compat::MenuModel": {
    "moar": 0e0,
    "start": 0e0,
    "parse": 2.853e0,
    "mbc": 0.001e0,
    "mast": 0.003e0,
    "ast": 0e0,
    "optimize": 0.001e0,
    "syntaxcheck": 0e0
  },
  "GTK::Roles::Properties": {
    "optimize": 0.001e0,
    "ast": 0e0,
    "syntaxcheck": 0e0,
    "parse": 3.048e0,
    "start": 0e0,
    "moar": 0e0,
    "mbc": 0e0,
    "mast": 0.003e0
  },
  "GTK::InfoBar": {
    "ast": 0e0,
    "optimize": 0.001e0,
    "syntaxcheck": 0e0,
    "parse": 4.14e0,
    "start": 0e0,
    "moar": 0e0,
    "mbc": 0.001e0,
    "mast": 0.003e0
  },
  "GTK::PageSetup": {
    "syntaxcheck": 0e0,
    "ast": 0e0,
    "optimize": 0.001e0,
    "mast": 0.003e0,
    "mbc": 0e0,
    "moar": 0e0,
    "parse": 3.058e0,
    "start": 0e0
  },
  "GTK::Raw::Image": {
    "ast": 0e0,
    "optimize": 0.001e0,
    "syntaxcheck": 0e0,
    "parse": 4.719e0,
    "start": 0e0,
    "moar": 0e0,
    "mast": 0.004e0,
    "mbc": 0.001e0
  },
  "GTK::Places": {
    "moar": 0e0,
    "start": 0e0,
    "parse": 4.499e0,
    "mbc": 0e0,
    "mast": 0.003e0,
    "ast": 0e0,
    "optimize": 0.001e0,
    "syntaxcheck": 0e0
  },
  "GTK::Roles::Data": {
    "ast": 0e0,
    "optimize": 0.001e0,
    "syntaxcheck": 0e0,
    "moar": 0e0,
    "start": 0e0,
    "parse": 2.755e0,
    "mast": 0.003e0,
    "mbc": 0.001e0
  },
  "Pango::AttrList": {
    "syntaxcheck": 0e0,
    "optimize": 0.001e0,
    "ast": 0e0,
    "mast": 0.003e0,
    "mbc": 0.001e0,
    "parse": 16.787e0,
    "start": 0e0,
    "moar": 0e0
  },
  "GTK::Roles::Signals::Overlay": {
    "start": 0e0,
    "parse": 2.942e0,
    "moar": 0e0,
    "mbc": 0.002e0,
    "mast": 0.008e0,
    "optimize": 0.001e0,
    "ast": 0e0,
    "syntaxcheck": 0e0
  },
  "GTK::Dialog::Raw::ColorChooser": {
    "syntaxcheck": 0e0,
    "optimize": 0.001e0,
    "ast": 0e0,
    "mbc": 0.001e0,
    "mast": 0.003e0,
    "moar": 0e0,
    "start": 0e0,
    "parse": 2.661e0
  },
  "GTK::Container": {
    "moar": 0e0,
    "parse": 4.505e0,
    "start": 0e0,
    "mast": 0.003e0,
    "mbc": 0.001e0,
    "optimize": 0.001e0,
    "ast": 0e0,
    "syntaxcheck": 0e0
  },
  "GTK::Raw::Adjustment": {
    "mbc": 0.001e0,
    "mast": 0.004e0,
    "start": 0e0,
    "parse": 3.938e0,
    "moar": 0e0,
    "syntaxcheck": 0e0,
    "optimize": 0.001e0,
    "ast": 0e0
  },
  "GTK::Roles::Buildable": {
    "mbc": 0.001e0,
    "mast": 0.003e0,
    "start": 0e0,
    "parse": 2.861e0,
    "moar": 0e0,
    "syntaxcheck": 0e0,
    "ast": 0e0,
    "optimize": 0.001e0
  },
  "GTK::IconView": {
    "optimize": 0.001e0,
    "ast": 0e0,
    "syntaxcheck": 0e0,
    "parse": 5.213e0,
    "start": 0e0,
    "moar": 0e0,
    "mbc": 0.001e0,
    "mast": 0.003e0
  },
  "GTK::Compat::X11_Types": {
    "optimize": 0.001e0,
    "ast": 0e0,
    "syntaxcheck": 0e0,
    "moar": 0e0,
    "parse": 2.327e0,
    "start": 0e0,
    "mast": 0.003e0,
    "mbc": 0.001e0
  },
  "GTK::Compat::Visual": {
    "syntaxcheck": 0e0,
    "ast": 0e0,
    "optimize": 0.002e0,
    "mast": 0.008e0,
    "mbc": 0.001e0,
    "parse": 2.611e0,
    "start": 0e0,
    "moar": 0e0
  },
  "GTK::Roles::FontChooser": {
    "syntaxcheck": 0e0,
    "ast": 0e0,
    "optimize": 0.001e0,
    "mast": 0.003e0,
    "mbc": 0e0,
    "moar": 0e0,
    "parse": 3.007e0,
    "start": 0e0
  },
  "GTK::Dialog::Raw::PageSetupUnix": {
    "optimize": 0.001e0,
    "ast": 0e0,
    "syntaxcheck": 0e0,
    "start": 0e0,
    "parse": 3.086e0,
    "moar": 0e0,
    "mast": 0.003e0,
    "mbc": 0.001e0
  },
  "GTK::ShortcutsGroup": {
    "parse": 4.047e0,
    "start": 0e0,
    "moar": 0e0,
    "mast": 0.008e0,
    "mbc": 0.001e0,
    "optimize": 0.002e0,
    "ast": 0e0,
    "syntaxcheck": 0e0
  },
  "GTK::Raw::TextView": {
    "syntaxcheck": 0e0,
    "optimize": 0.002e0,
    "ast": 0e0,
    "mbc": 0.001e0,
    "mast": 0.005e0,
    "moar": 0e0,
    "parse": 8.568e0,
    "start": 0e0
  },
  "GTK::Roles::Signals::TextTag": {
    "syntaxcheck": 0e0,
    "optimize": 0.001e0,
    "ast": 0e0,
    "mbc": 0e0,
    "mast": 0.003e0,
    "start": 0e0,
    "parse": 2.985e0,
    "moar": 0e0
  },
  "GTK::Raw::CellArea": {
    "mast": 0.004e0,
    "mbc": 0.001e0,
    "start": 0e0,
    "parse": 5.832e0,
    "moar": 0e0,
    "syntaxcheck": 0e0,
    "ast": 0e0,
    "optimize": 0.002e0
  },
  "GTK::Compat::Raw::KeyFile": {
    "mast": 0.009e0,
    "mbc": 0.006e0,
    "moar": 0e0,
    "parse": 4.999e0,
    "start": 0e0,
    "syntaxcheck": 0e0,
    "ast": 0e0,
    "optimize": 0.002e0
  },
  "GTK::Raw::MenuToolButton": {
    "optimize": 0.001e0,
    "ast": 0e0,
    "syntaxcheck": 0e0,
    "start": 0e0,
    "parse": 3.088e0,
    "moar": 0e0,
    "mast": 0.003e0,
    "mbc": 0.001e0
  },
  "GTK::CellAreaContext": {
    "ast": 0e0,
    "optimize": 0.002e0,
    "syntaxcheck": 0e0,
    "parse": 3.085e0,
    "start": 0e0,
    "moar": 0e0,
    "mbc": 0.001e0,
    "mast": 0.008e0
  },
  "GTK::Raw::ToolItemGroup": {
    "ast": 0e0,
    "optimize": 0.001e0,
    "syntaxcheck": 0e0,
    "start": 0e0,
    "parse": 3.906e0,
    "moar": 0e0,
    "mbc": 0.001e0,
    "mast": 0.003e0
  },
  "GTK::Dialog::AppChooser": {
    "syntaxcheck": 0e0,
    "ast": 0e0,
    "optimize": 0.002e0,
    "mast": 0.008e0,
    "mbc": 0.004e0,
    "start": 0e0,
    "parse": 4.303e0,
    "moar": 0e0
  },
  "GTK::Raw::Widget": {
    "optimize": 0.004e0,
    "ast": 0e0,
    "syntaxcheck": 0e0,
    "moar": 0e0,
    "start": 0e0,
    "parse": 20.888e0,
    "mbc": 0.003e0,
    "mast": 0.008e0
  },
  "GTK::Overlay": {
    "mbc": 0.001e0,
    "mast": 0.003e0,
    "parse": 4.354e0,
    "start": 0e0,
    "moar": 0e0,
    "syntaxcheck": 0e0,
    "ast": 0e0,
    "optimize": 0.001e0
  },
  "GTK::Dialog::Message": {
    "syntaxcheck": 0e0,
    "ast": 0e0,
    "optimize": 0.001e0,
    "mast": 0.004e0,
    "mbc": 0.001e0,
    "start": 0e0,
    "parse": 4.325e0,
    "moar": 0e0
  },
  "GTK::Raw::Editable": {
    "syntaxcheck": 0e0,
    "ast": 0e0,
    "optimize": 0.001e0,
    "mast": 0.003e0,
    "mbc": 0.001e0,
    "start": 0e0,
    "parse": 3.654e0,
    "moar": 0e0
  },
  "GTK::Builder::Widget": {
    "ast": 0e0,
    "optimize": 0.002e0,
    "syntaxcheck": 0e0,
    "moar": 0e0,
    "parse": 2.302e0,
    "start": 0e0,
    "mbc": 0.001e0,
    "mast": 0.008e0
  },
  "GTK::Roles::Signals::TreeView": {
    "syntaxcheck": 0e0,
    "optimize": 0.001e0,
    "ast": 0e0,
    "mbc": 0.001e0,
    "mast": 0.003e0,
    "parse": 3.26e0,
    "start": 0e0,
    "moar": 0e0
  },
  "GTK::Scrollbar": {
    "syntaxcheck": 0e0,
    "optimize": 0.001e0,
    "ast": 0e0,
    "mast": 0.003e0,
    "mbc": 0.001e0,
    "start": 0e0,
    "parse": 3.845e0,
    "moar": 0e0
  },
  "GTK::Compat::Raw::Window": {
    "mbc": 0.002e0,
    "mast": 0.012e0,
    "start": 0e0,
    "parse": 11.419e0,
    "moar": 0e0,
    "syntaxcheck": 0e0,
    "optimize": 0.004e0,
    "ast": 0e0
  },
  "GTK::PrintOperation": {
    "mbc": 0.001e0,
    "mast": 0.003e0,
    "start": 0e0,
    "parse": 3.895e0,
    "moar": 0e0,
    "syntaxcheck": 0e0,
    "ast": 0e0,
    "optimize": 0.001e0
  },
  "GTK::Raw::Grid": {
    "optimize": 0.001e0,
    "ast": 0e0,
    "syntaxcheck": 0e0,
    "moar": 0e0,
    "start": 0e0,
    "parse": 4.172e0,
    "mbc": 0.001e0,
    "mast": 0.003e0
  },
  "GTK::VolumeButton": {
    "syntaxcheck": 0e0,
    "optimize": 0.001e0,
    "ast": 0e0,
    "mast": 0.003e0,
    "mbc": 0.001e0,
    "parse": 4.09e0,
    "start": 0e0,
    "moar": 0e0
  },
  "GTK::Raw::Buildable": {
    "syntaxcheck": 0e0,
    "optimize": 0.001e0,
    "ast": 0e0,
    "mbc": 0.001e0,
    "mast": 0.003e0,
    "moar": 0e0,
    "start": 0e0,
    "parse": 3.449e0
  },
  "GTK::Compat::Raw::Binding": {
    "syntaxcheck": 0e0,
    "optimize": 0.002e0,
    "ast": 0e0,
    "mast": 0.008e0,
    "mbc": 0.001e0,
    "moar": 0e0,
    "start": 0e0,
    "parse": 2.905e0
  },
  "GTK::Raw::RecentFilter": {
    "mbc": 0.001e0,
    "mast": 0.008e0,
    "moar": 0e0,
    "start": 0e0,
    "parse": 3.483e0,
    "syntaxcheck": 0e0,
    "ast": 0e0,
    "optimize": 0.002e0
  },
  "GTK::Compat::Raw::Icon": {
    "parse": 2.787e0,
    "start": 0e0,
    "moar": 0e0,
    "mbc": 0.001e0,
    "mast": 0.008e0,
    "ast": 0e0,
    "optimize": 0.002e0,
    "syntaxcheck": 0e0
  },
  "GTK::TextBuffer": {
    "syntaxcheck": 0e0,
    "ast": 0e0,
    "optimize": 0.001e0,
    "mast": 0.005e0,
    "mbc": 0.001e0,
    "parse": 5.017e0,
    "start": 0e0,
    "moar": 0e0
  },
  "GTK::Raw::Revealer": {
    "mbc": 0.001e0,
    "mast": 0.003e0,
    "moar": 0e0,
    "start": 0e0,
    "parse": 3.308e0,
    "syntaxcheck": 0e0,
    "optimize": 0.001e0,
    "ast": 0e0
  },
  "GTK::Builder::Label": {
    "optimize": 0.002e0,
    "ast": 0e0,
    "syntaxcheck": 0e0,
    "start": 0e0,
    "parse": 2.197e0,
    "moar": 0e0,
    "mbc": 0.001e0,
    "mast": 0.008e0
  },
  "GTK::ActionBar": {
    "optimize": 0.001e0,
    "ast": 0e0,
    "syntaxcheck": 0e0,
    "parse": 4.017e0,
    "start": 0e0,
    "moar": 0e0,
    "mast": 0.003e0,
    "mbc": 0.001e0
  },
  "GTK::Raw::CSS_Section": {
    "mbc": 0.001e0,
    "mast": 0.01e0,
    "parse": 3.269e0,
    "start": 0e0,
    "moar": 0e0,
    "syntaxcheck": 0e0,
    "optimize": 0.003e0,
    "ast": 0e0
  },
  "GTK::RecentFilter": {
    "mbc": 0.002e0,
    "mast": 0.012e0,
    "parse": 2.788e0,
    "start": 0e0,
    "moar": 0e0,
    "syntaxcheck": 0e0,
    "ast": 0e0,
    "optimize": 0.002e0
  },
  "GTK::Compat::Raw::Settings": {
    "syntaxcheck": 0e0,
    "optimize": 0.002e0,
    "ast": 0e0,
    "mast": 0.016e0,
    "mbc": 0.002e0,
    "start": 0e0,
    "parse": 4.794e0,
    "moar": 0e0
  },
  "GTK::Fixed": {
    "ast": 0e0,
    "optimize": 0.001e0,
    "syntaxcheck": 0e0,
    "parse": 3.931e0,
    "start": 0e0,
    "moar": 0e0,
    "mbc": 0.001e0,
    "mast": 0.003e0
  },
  "GTK::Raw::Builder": {
    "moar": 0e0,
    "parse": 4.618e0,
    "start": 0e0,
    "mbc": 0.001e0,
    "mast": 0.004e0,
    "optimize": 0.001e0,
    "ast": 0e0,
    "syntaxcheck": 0e0
  },
  "GTK::Roles::Signals::Statusbar": {
    "syntaxcheck": 0e0,
    "ast": 0e0,
    "optimize": 0.001e0,
    "mast": 0.003e0,
    "mbc": 0e0,
    "parse": 2.836e0,
    "start": 0e0,
    "moar": 0e0
  },
  "GTK::Compat::DragContext": {
    "ast": 0e0,
    "optimize": 0.001e0,
    "syntaxcheck": 0e0,
    "start": 0e0,
    "parse": 3.183e0,
    "moar": 0e0,
    "mbc": 0e0,
    "mast": 0.003e0
  },
  "GTK::Dialog::About": {
    "syntaxcheck": 0e0,
    "optimize": 0.001e0,
    "ast": 0e0,
    "mbc": 0.001e0,
    "mast": 0.003e0,
    "moar": 0e0,
    "parse": 4.634e0,
    "start": 0e0
  },
  "GTK::CellView": {
    "ast": 0e0,
    "optimize": 0.002e0,
    "syntaxcheck": 0e0,
    "moar": 0e0,
    "parse": 4.232e0,
    "start": 0e0,
    "mbc": 0.001e0,
    "mast": 0.008e0
  },
  "GTK::Calendar": {
    "start": 0e0,
    "parse": 3.994e0,
    "moar": 0e0,
    "mbc": 0.001e0,
    "mast": 0.003e0,
    "optimize": 0.001e0,
    "ast": 0e0,
    "syntaxcheck": 0e0
  },
  "GTK::Compat::Raw::MenuModel": {
    "syntaxcheck": 0e0,
    "ast": 0e0,
    "optimize": 0.001e0,
    "mbc": 0.001e0,
    "mast": 0.003e0,
    "parse": 3.327e0,
    "start": 0e0,
    "moar": 0e0
  },
  "GTK::SeparatorToolItem": {
    "syntaxcheck": 0e0,
    "optimize": 0.001e0,
    "ast": 0e0,
    "mast": 0.003e0,
    "mbc": 0.001e0,
    "moar": 0e0,
    "start": 0e0,
    "parse": 3.993e0
  },
  "GTK::Compat::Raw::X11_Window": {
    "syntaxcheck": 0e0,
    "optimize": 0.001e0,
    "ast": 0e0,
    "mast": 0.003e0,
    "mbc": 0.001e0,
    "parse": 3.097e0,
    "start": 0e0,
    "moar": 0e0
  },
  "GTK::Roles::Signals::ComboBox": {
    "mbc": 0e0,
    "mast": 0.003e0,
    "moar": 0e0,
    "parse": 3.029e0,
    "start": 0e0,
    "syntaxcheck": 0e0,
    "optimize": 0.001e0,
    "ast": 0e0
  },
  "GTK::Compat::Raw::X11_Display": {
    "syntaxcheck": 0e0,
    "ast": 0e0,
    "optimize": 0.001e0,
    "mbc": 0.001e0,
    "mast": 0.003e0,
    "start": 0e0,
    "parse": 3.321e0,
    "moar": 0e0
  },
  "GTK::Raw::CellRendererCombo": {
    "start": 0e0,
    "parse": 2.964e0,
    "moar": 0e0,
    "mast": 0.003e0,
    "mbc": 0.001e0,
    "ast": 0e0,
    "optimize": 0.001e0,
    "syntaxcheck": 0e0
  },
  "GTK::SeparatorMenuItem": {
    "mast": 0.003e0,
    "mbc": 0.001e0,
    "moar": 0e0,
    "start": 0e0,
    "parse": 3.889e0,
    "syntaxcheck": 0e0,
    "ast": 0e0,
    "optimize": 0.001e0
  },
  "Pango::Raw::Types": {
    "mast": 0.011e0,
    "mbc": 0.004e0,
    "start": 0e0,
    "parse": 0.985e0,
    "moar": 0e0,
    "syntaxcheck": 0e0,
    "ast": 0e0,
    "optimize": 0.004e0
  },
  "GTK::Compat::Raw::Rectangle": {
    "start": 0e0,
    "parse": 2.753e0,
    "moar": 0e0,
    "mast": 0.003e0,
    "mbc": 0.001e0,
    "optimize": 0.001e0,
    "ast": 0e0,
    "syntaxcheck": 0e0
  },
  "GTK::Dialog::Raw::AppChooser": {
    "moar": 0e0,
    "parse": 3.002e0,
    "start": 0e0,
    "mbc": 0.001e0,
    "mast": 0.007e0,
    "ast": 0e0,
    "optimize": 0.002e0,
    "syntaxcheck": 0e0
  },
  "GTK::Raw::TreeModelSort": {
    "mbc": 0.001e0,
    "mast": 0.008e0,
    "moar": 0e0,
    "start": 0e0,
    "parse": 3.26e0,
    "syntaxcheck": 0e0,
    "ast": 0e0,
    "optimize": 0.002e0
  },
  "GTK::WindowGroup": {
    "moar": 0e0,
    "parse": 2.803e0,
    "start": 0e0,
    "mast": 0.008e0,
    "mbc": 0.001e0,
    "optimize": 0.002e0,
    "ast": 0e0,
    "syntaxcheck": 0e0
  },
  "GTK::Compat::Raw::Cursor": {
    "mbc": 0.001e0,
    "mast": 0.003e0,
    "start": 0e0,
    "parse": 3.089e0,
    "moar": 0e0,
    "syntaxcheck": 0e0,
    "ast": 0e0,
    "optimize": 0.001e0
  },
  "GTK::Raw::Calendar": {
    "moar": 0e0,
    "start": 0e0,
    "parse": 3.71e0,
    "mbc": 0.001e0,
    "mast": 0.003e0,
    "ast": 0e0,
    "optimize": 0.001e0,
    "syntaxcheck": 0e0
  },
  "GTK::Raw::CSSProvider": {
    "mast": 0.003e0,
    "mbc": 0.001e0,
    "parse": 3.304e0,
    "start": 0e0,
    "moar": 0e0,
    "syntaxcheck": 0e0,
    "ast": 0e0,
    "optimize": 0.001e0
  },
  "GTK::Raw::PrintJob": {
    "syntaxcheck": 0e0,
    "optimize": 0.003e0,
    "ast": 0e0,
    "mbc": 0.002e0,
    "mast": 0.009e0,
    "moar": 0e0,
    "parse": 4.859e0,
    "start": 0e0
  },
  "GTK::FileFilter": {
    "mbc": 0.001e0,
    "mast": 0.003e0,
    "moar": 0e0,
    "start": 0e0,
    "parse": 2.996e0,
    "syntaxcheck": 0e0,
    "ast": 0e0,
    "optimize": 0.001e0
  },
  "GTK::CheckButton": {
    "moar": 0e0,
    "parse": 4.211e0,
    "start": 0e0,
    "mbc": 0.001e0,
    "mast": 0.003e0,
    "ast": 0e0,
    "optimize": 0.001e0,
    "syntaxcheck": 0e0
  },
  "GTK::Raw::FileChooser": {
    "syntaxcheck": 0e0,
    "optimize": 0.002e0,
    "ast": 0e0,
    "mast": 0.005e0,
    "mbc": 0.001e0,
    "start": 0e0,
    "parse": 7.111e0,
    "moar": 0e0
  },
  "GTK::Raw::Overlay": {
    "moar": 0e0,
    "start": 0e0,
    "parse": 3.105e0,
    "mbc": 0.001e0,
    "mast": 0.003e0,
    "ast": 0e0,
    "optimize": 0.001e0,
    "syntaxcheck": 0e0
  },
  "GTK::Builder::Frame": {
    "moar": 0e0,
    "start": 0e0,
    "parse": 2.233e0,
    "mast": 0.008e0,
    "mbc": 0.001e0,
    "ast": 0e0,
    "optimize": 0.002e0,
    "syntaxcheck": 0e0
  },
  "GTK::Roles::TreeSortable": {
    "mbc": 0e0,
    "mast": 0.003e0,
    "parse": 2.911e0,
    "start": 0e0,
    "moar": 0e0,
    "syntaxcheck": 0e0,
    "optimize": 0.001e0,
    "ast": 0e0
  },
  "GTK::Raw::PaperSize": {
    "moar": 0e0,
    "start": 0e0,
    "parse": 4.582e0,
    "mast": 0.004e0,
    "mbc": 0.001e0,
    "ast": 0e0,
    "optimize": 0.001e0,
    "syntaxcheck": 0e0
  },
  "GTK::Selection": {
    "parse": 3.434e0,
    "start": 0e0,
    "moar": 0e0,
    "mbc": 0.001e0,
    "mast": 0.007e0,
    "optimize": 0.002e0,
    "ast": 0e0,
    "syntaxcheck": 0e0
  },
  "GTK::CellRendererProgress": {
    "ast": 0e0,
    "optimize": 0.001e0,
    "syntaxcheck": 0e0,
    "moar": 0e0,
    "start": 0e0,
    "parse": 3.056e0,
    "mast": 0.003e0,
    "mbc": 0.001e0
  },
  "GTK::Clipboard": {
    "mast": 0.003e0,
    "mbc": 0.001e0,
    "moar": 0e0,
    "parse": 3.284e0,
    "start": 0e0,
    "syntaxcheck": 0e0,
    "ast": 0e0,
    "optimize": 0.001e0
  },
  "GTK::Compat::DisplayManager": {
    "mast": 0.008e0,
    "mbc": 0.001e0,
    "start": 0e0,
    "parse": 2.767e0,
    "moar": 0e0,
    "syntaxcheck": 0e0,
    "ast": 0e0,
    "optimize": 0.002e0
  },
  "GTK::Builder::MenuShell": {
    "moar": 0e0,
    "parse": 2.108e0,
    "start": 0e0,
    "mast": 0.008e0,
    "mbc": 0.001e0,
    "optimize": 0.002e0,
    "ast": 0e0,
    "syntaxcheck": 0e0
  },
  "GTK::Roles::Signals::CellArea": {
    "moar": 0e0,
    "start": 0e0,
    "parse": 3.579e0,
    "mast": 0.003e0,
    "mbc": 0e0,
    "optimize": 0.001e0,
    "ast": 0e0,
    "syntaxcheck": 0e0
  },
  "GTK::Raw::CellRendererPixbuf": {
    "parse": 2.715e0,
    "start": 0e0,
    "moar": 0e0,
    "mast": 0.007e0,
    "mbc": 0.001e0,
    "optimize": 0.002e0,
    "ast": 0e0,
    "syntaxcheck": 0e0
  },
  "GTK::Compat::Raw::Threads": {
    "start": 0e0,
    "parse": 3.052e0,
    "moar": 0e0,
    "mbc": 0.001e0,
    "mast": 0.016e0,
    "optimize": 0.002e0,
    "ast": 0e0,
    "syntaxcheck": 0e0
  },
  "GTK::Roles::Signals::Scale": {
    "ast": 0e0,
    "optimize": 0.001e0,
    "syntaxcheck": 0e0,
    "moar": 0e0,
    "parse": 2.919e0,
    "start": 0e0,
    "mbc": 0e0,
    "mast": 0.003e0
  },
  "GTK::TreeStore": {
    "syntaxcheck": 0e0,
    "ast": 0e0,
    "optimize": 0.001e0,
    "mbc": 0.001e0,
    "mast": 0.003e0,
    "moar": 0e0,
    "parse": 3.376e0,
    "start": 0e0
  },
  "GTK::Raw::CellRenderer": {
    "ast": 0e0,
    "optimize": 0.001e0,
    "syntaxcheck": 0e0,
    "parse": 4.512e0,
    "start": 0e0,
    "moar": 0e0,
    "mast": 0.004e0,
    "mbc": 0.001e0
  },
  "GTK::ButtonBox": {
    "syntaxcheck": 0e0,
    "ast": 0e0,
    "optimize": 0.001e0,
    "mbc": 0.001e0,
    "mast": 0.003e0,
    "parse": 4.052e0,
    "start": 0e0,
    "moar": 0e0
  },
  "GTK::Compat::Raw::Event": {
    "moar": 0e0,
    "start": 0e0,
    "parse": 5.665e0,
    "mast": 0.012e0,
    "mbc": 0.002e0,
    "optimize": 0.002e0,
    "ast": 0e0,
    "syntaxcheck": 0e0
  },
  "GTK::Raw::SeparatorToolItem": {
    "start": 0e0,
    "parse": 2.872e0,
    "moar": 0e0,
    "mast": 0.003e0,
    "mbc": 0.001e0,
    "ast": 0e0,
    "optimize": 0.001e0,
    "syntaxcheck": 0e0
  },
  "GTK::Compat::Raw::Monitor": {
    "ast": 0e0,
    "optimize": 0.002e0,
    "syntaxcheck": 0e0,
    "parse": 3.177e0,
    "start": 0e0,
    "moar": 0e0,
    "mbc": 0.001e0,
    "mast": 0.008e0
  },
  "GTK::Separator": {
    "syntaxcheck": 0e0,
    "ast": 0e0,
    "optimize": 0.001e0,
    "mast": 0.003e0,
    "mbc": 0.001e0,
    "start": 0e0,
    "parse": 3.834e0,
    "moar": 0e0
  },
  "GTK::Roles::Signals::PrintOperation": {
    "start": 0e0,
    "parse": 4.089e0,
    "moar": 0e0,
    "mast": 0.003e0,
    "mbc": 0e0,
    "ast": 0e0,
    "optimize": 0.001e0,
    "syntaxcheck": 0e0
  },
  "GTK::Raw::ActionBar": {
    "syntaxcheck": 0e0,
    "optimize": 0.001e0,
    "ast": 0e0,
    "mbc": 0.001e0,
    "mast": 0.003e0,
    "moar": 0e0,
    "parse": 3.009e0,
    "start": 0e0
  },
  "GTK::EntryCompletion": {
    "syntaxcheck": 0e0,
    "ast": 0e0,
    "optimize": 0.002e0,
    "mast": 0.008e0,
    "mbc": 0.001e0,
    "parse": 4.115e0,
    "start": 0e0,
    "moar": 0e0
  },
  "GTK::HeaderBar": {
    "moar": 0e0,
    "parse": 4.008e0,
    "start": 0e0,
    "mbc": 0.001e0,
    "mast": 0.003e0,
    "optimize": 0.001e0,
    "ast": 0e0,
    "syntaxcheck": 0e0
  },
  "GTK::Raw::MenuItem": {
    "ast": 0e0,
    "optimize": 0.001e0,
    "syntaxcheck": 0e0,
    "start": 0e0,
    "parse": 4.071e0,
    "moar": 0e0,
    "mbc": 0.001e0,
    "mast": 0.004e0
  },
  "GTK::Roles::Signals::TextBuffer": {
    "ast": 0e0,
    "optimize": 0.001e0,
    "syntaxcheck": 0e0,
    "moar": 0e0,
    "start": 0e0,
    "parse": 4.392e0,
    "mbc": 0.001e0,
    "mast": 0.003e0
  },
  "GTK::CSS_Section": {
    "optimize": 0.002e0,
    "ast": 0e0,
    "syntaxcheck": 0e0,
    "moar": 0e0,
    "start": 0e0,
    "parse": 2.693e0,
    "mast": 0.008e0,
    "mbc": 0.001e0
  },
  "GTK::Compat::Raw::Value": {
    "mbc": 0.001e0,
    "mast": 0.005e0,
    "moar": 0e0,
    "start": 0e0,
    "parse": 5.047e0,
    "syntaxcheck": 0e0,
    "ast": 0e0,
    "optimize": 0.003e0
  },
  "GTK::Dialog::FontChooser": {
    "syntaxcheck": 0e0,
    "ast": 0e0,
    "optimize": 0.001e0,
    "mast": 0.003e0,
    "mbc": 0.001e0,
    "moar": 0e0,
    "start": 0e0,
    "parse": 4.276e0
  },
  "GTK::BuilderWidgets": {
    "moar": 0e0,
    "parse": 2.357e0,
    "start": 0e0,
    "mast": 0.008e0,
    "mbc": 0.001e0,
    "optimize": 0.002e0,
    "ast": 0e0,
    "syntaxcheck": 0e0
  },
  "GTK::MenuButton": {
    "syntaxcheck": 0e0,
    "optimize": 0.001e0,
    "ast": 0e0,
    "mast": 0.003e0,
    "mbc": 0.001e0,
    "parse": 4.658e0,
    "start": 0e0,
    "moar": 0e0
  },
  "GTK::TreeSelection": {
    "syntaxcheck": 0e0,
    "ast": 0e0,
    "optimize": 0.001e0,
    "mast": 0.003e0,
    "mbc": 0.001e0,
    "start": 0e0,
    "parse": 3.104e0,
    "moar": 0e0
  },
  "GTK::Builder::Base": {
    "ast": 0e0,
    "optimize": 0.002e0,
    "syntaxcheck": 0e0,
    "start": 0e0,
    "parse": 2.68e0,
    "moar": 0e0,
    "mast": 0.008e0,
    "mbc": 0.001e0
  },
  "GTK::Compat::Roles::Icon": {
    "moar": 0e0,
    "parse": 2.593e0,
    "start": 0e0,
    "mast": 0.008e0,
    "mbc": 0.001e0,
    "ast": 0e0,
    "optimize": 0.002e0,
    "syntaxcheck": 0e0
  },
  "GTK::Roles::Signals::Places": {
    "parse": 3.712e0,
    "start": 0e0,
    "moar": 0e0,
    "mast": 0.003e0,
    "mbc": 0.001e0,
    "ast": 0e0,
    "optimize": 0.001e0,
    "syntaxcheck": 0e0
  },
  "GTK::CellRendererToggle": {
    "syntaxcheck": 0e0,
    "optimize": 0.002e0,
    "ast": 0e0,
    "mbc": 0.002e0,
    "mast": 0.008e0,
    "moar": 0e0,
    "start": 0e0,
    "parse": 2.985e0
  },
  "GTK::StyleContext": {
    "syntaxcheck": 0e0,
    "optimize": 0.001e0,
    "ast": 0e0,
    "mast": 0.003e0,
    "mbc": 0.001e0,
    "parse": 4.95e0,
    "start": 0e0,
    "moar": 0e0
  },
  "GTK::Raw::FontButton": {
    "parse": 3.665e0,
    "start": 0e0,
    "moar": 0e0,
    "mast": 0.003e0,
    "mbc": 0.001e0,
    "optimize": 0.001e0,
    "ast": 0e0,
    "syntaxcheck": 0e0
  },
  "GTK::Dialog::FileChooser": {
    "syntaxcheck": 0e0,
    "optimize": 0.002e0,
    "ast": 0e0,
    "mast": 0.008e0,
    "mbc": 0.001e0,
    "start": 0e0,
    "parse": 4.456e0,
    "moar": 0e0
  },
  "GTK::Roles::StyleProvider": {
    "mbc": 0.001e0,
    "mast": 0.003e0,
    "parse": 3.072e0,
    "start": 0e0,
    "moar": 0e0,
    "syntaxcheck": 0e0,
    "optimize": 0.001e0,
    "ast": 0e0
  },
  "GTK::Roles::References": {
    "ast": 0e0,
    "optimize": 0.001e0,
    "syntaxcheck": 0e0,
    "parse": 2.728e0,
    "start": 0e0,
    "moar": 0e0,
    "mast": 0.003e0,
    "mbc": 0.001e0
  },
  "GTK::Compat::Window": {
    "mast": 0.003e0,
    "mbc": 0.001e0,
    "start": 0e0,
    "parse": 5.259e0,
    "moar": 0e0,
    "syntaxcheck": 0e0,
    "optimize": 0.001e0,
    "ast": 0e0
  },
  "GTK::Frame": {
    "mast": 0.003e0,
    "mbc": 0.001e0,
    "start": 0e0,
    "parse": 4.032e0,
    "moar": 0e0,
    "syntaxcheck": 0e0,
    "optimize": 0.001e0,
    "ast": 0e0
  },
  "GTK::Roles::Signals::Application": {
    "syntaxcheck": 0e0,
    "ast": 0e0,
    "optimize": 0.001e0,
    "mbc": 0.001e0,
    "mast": 0.003e0,
    "moar": 0e0,
    "start": 0e0,
    "parse": 2.939e0
  },
  "GTK::Raw::Tooltip": {
    "ast": 0e0,
    "optimize": 0.002e0,
    "syntaxcheck": 0e0,
    "start": 0e0,
    "parse": 3.219e0,
    "moar": 0e0,
    "mbc": 0.001e0,
    "mast": 0.013e0
  },
  "GTK::Raw::Utils": {
    "optimize": 0.002e0,
    "ast": 0e0,
    "syntaxcheck": 0e0,
    "start": 0e0,
    "parse": 3.091e0,
    "moar": 0e0,
    "mast": 0.006e0,
    "mbc": 0.001e0
  },
  "GTK::Raw::DnD": {
    "moar": 0e0,
    "start": 0e0,
    "parse": 3.787e0,
    "mbc": 0.001e0,
    "mast": 0.004e0,
    "ast": 0e0,
    "optimize": 0.001e0,
    "syntaxcheck": 0e0
  },
  "GTK::Raw::Clipboard": {
    "mast": 0.004e0,
    "mbc": 0.001e0,
    "parse": 5.05e0,
    "start": 0e0,
    "moar": 0e0,
    "syntaxcheck": 0e0,
    "ast": 0e0,
    "optimize": 0.001e0
  },
  "GTK::SpinButton": {
    "syntaxcheck": 0e0,
    "ast": 0e0,
    "optimize": 0.001e0,
    "mbc": 0.001e0,
    "mast": 0.003e0,
    "start": 0e0,
    "parse": 4.367e0,
    "moar": 0e0
  },
  "GTK::LinkButton": {
    "moar": 0e0,
    "start": 0e0,
    "parse": 4.032e0,
    "mbc": 0.001e0,
    "mast": 0.003e0,
    "ast": 0e0,
    "optimize": 0.001e0,
    "syntaxcheck": 0e0
  },
  "GTK::TargetList": {
    "syntaxcheck": 0e0,
    "optimize": 0.001e0,
    "ast": 0e0,
    "mast": 0.003e0,
    "mbc": 0e0,
    "moar": 0e0,
    "start": 0e0,
    "parse": 2.898e0
  },
  "GTK::Raw::Bin": {
    "syntaxcheck": 0e0,
    "ast": 0e0,
    "optimize": 0.001e0,
    "mast": 0.003e0,
    "mbc": 0.001e0,
    "parse": 2.735e0,
    "start": 0e0,
    "moar": 0e0
  },
  "GTK::Raw::FileFilter": {
    "ast": 0e0,
    "optimize": 0.001e0,
    "syntaxcheck": 0e0,
    "moar": 0e0,
    "start": 0e0,
    "parse": 3.489e0,
    "mast": 0.003e0,
    "mbc": 0.001e0
  },
  "GTK::Compat::Raw::FrameTimings": {
    "moar": 0e0,
    "start": 0e0,
    "parse": 2.838e0,
    "mbc": 0.001e0,
    "mast": 0.008e0,
    "ast": 0e0,
    "optimize": 0.002e0,
    "syntaxcheck": 0e0
  },
  "GTK::Raw::Dialog": {
    "mast": 0.003e0,
    "mbc": 0.001e0,
    "parse": 3.721e0,
    "start": 0e0,
    "moar": 0e0,
    "syntaxcheck": 0e0,
    "optimize": 0.001e0,
    "ast": 0e0
  },
  "GTK::Raw::TreeSelection": {
    "moar": 0e0,
    "start": 0e0,
    "parse": 4.036e0,
    "mast": 0.003e0,
    "mbc": 0.001e0,
    "ast": 0e0,
    "optimize": 0.001e0,
    "syntaxcheck": 0e0
  },
  "GTK::Raw::PrintOperation": {
    "moar": 0e0,
    "parse": 5.126e0,
    "start": 0e0,
    "mbc": 0.001e0,
    "mast": 0.004e0,
    "ast": 0e0,
    "optimize": 0.001e0,
    "syntaxcheck": 0e0
  },
  "SUMMARY": {
    "user": 2593.88e0,
    "sys": 240.78e0,
    "real": 1972.5e0
  },
  "GTK::Raw::Offscreen": {
    "ast": 0e0,
    "optimize": 0.001e0,
    "syntaxcheck": 0e0,
    "start": 0e0,
    "parse": 2.88e0,
    "moar": 0e0,
    "mbc": 0.001e0,
    "mast": 0.003e0
  },
  "GTK::Roles::Signals::CSSProvider": {
    "optimize": 0.001e0,
    "ast": 0e0,
    "syntaxcheck": 0e0,
    "moar": 0e0,
    "start": 0e0,
    "parse": 2.939e0,
    "mbc": 0e0,
    "mast": 0.003e0
  },
  "GTK::ShortcutsShortcut": {
    "optimize": 0.002e0,
    "ast": 0e0,
    "syntaxcheck": 0e0,
    "moar": 0e0,
    "parse": 4.082e0,
    "start": 0e0,
    "mbc": 0.001e0,
    "mast": 0.008e0
  },
  "GTK::Compat::Variant": {
    "syntaxcheck": 0e0,
    "ast": 0e0,
    "optimize": 0.004e0,
    "mbc": 0.007e0,
    "mast": 0.011e0,
    "moar": 0e0,
    "start": 0e0,
    "parse": 3.093e0
  },
  "GTK::Raw::Menu": {
    "parse": 4.91e0,
    "start": 0e0,
    "moar": 0e0,
    "mbc": 0.001e0,
    "mast": 0.004e0,
    "optimize": 0.001e0,
    "ast": 0e0,
    "syntaxcheck": 0e0
  },
  "GTK::Compat::Raw::DisplayManager": {
    "ast": 0e0,
    "optimize": 0.002e0,
    "syntaxcheck": 0e0,
    "parse": 2.698e0,
    "start": 0e0,
    "moar": 0e0,
    "mbc": 0.001e0,
    "mast": 0.008e0
  },
  "GTK::ColorChooser": {
    "syntaxcheck": 0e0,
    "ast": 0e0,
    "optimize": 0.001e0,
    "mast": 0.003e0,
    "mbc": 0.001e0,
    "moar": 0e0,
    "start": 0e0,
    "parse": 4.041e0
  },
  "GTK::Raw::EntryCompletion": {
    "syntaxcheck": 0e0,
    "optimize": 0.002e0,
    "ast": 0e0,
    "mast": 0.009e0,
    "mbc": 0.002e0,
    "moar": 0e0,
    "start": 0e0,
    "parse": 4.523e0
  },
  "GTK::Raw::CellRendererToggle": {
    "moar": 0e0,
    "parse": 3.175e0,
    "start": 0e0,
    "mast": 0.008e0,
    "mbc": 0.001e0,
    "optimize": 0.002e0,
    "ast": 0e0,
    "syntaxcheck": 0e0
  },
  "GTK::Raw::IconTheme": {
    "syntaxcheck": 0e0,
    "optimize": 0.002e0,
    "ast": 0e0,
    "mast": 0.004e0,
    "mbc": 0.001e0,
    "moar": 0e0,
    "start": 0e0,
    "parse": 6.501e0
  },
  "GTK::Raw::EntryBuffer": {
    "syntaxcheck": 0e0,
    "ast": 0e0,
    "optimize": 0.001e0,
    "mast": 0.003e0,
    "mbc": 0.001e0,
    "parse": 3.581e0,
    "start": 0e0,
    "moar": 0e0
  },
  "GTK::CellRendererSpinner": {
    "optimize": 0.002e0,
    "ast": 0e0,
    "syntaxcheck": 0e0,
    "moar": 0e0,
    "start": 0e0,
    "parse": 2.925e0,
    "mbc": 0.001e0,
    "mast": 0.008e0
  },
  "GTK::Raw::Expander": {
    "moar": 0e0,
    "start": 0e0,
    "parse": 3.961e0,
    "mast": 0.003e0,
    "mbc": 0.001e0,
    "optimize": 0.001e0,
    "ast": 0e0,
    "syntaxcheck": 0e0
  },
  "GTK::Raw::Types": {
    "ast": 0e0,
    "optimize": 0.013e0,
    "syntaxcheck": 0e0,
    "start": 0e0,
    "parse": 10.805e0,
    "moar": 0e0,
    "mbc": 0.008e0,
    "mast": 0.02e0
  },
  "GTK::Raw::Render": {
    "parse": 4.253e0,
    "start": 0e0,
    "moar": 0e0,
    "mast": 0.004e0,
    "mbc": 0.001e0,
    "optimize": 0.001e0,
    "ast": 0e0,
    "syntaxcheck": 0e0
  },
  "GTK::DragContext": {
    "mbc": 0.001e0,
    "mast": 0.003e0,
    "parse": 2.937e0,
    "start": 0e0,
    "moar": 0e0,
    "syntaxcheck": 0e0,
    "optimize": 0.001e0,
    "ast": 0e0
  },
  "GTK::Roles::Protection": {
    "syntaxcheck": 0e0,
    "optimize": 0.002e0,
    "ast": 0e0,
    "mbc": 0.001e0,
    "mast": 0.008e0,
    "parse": 1.033e0,
    "start": 0e0,
    "moar": 0e0
  },
  "GTK::Compat::Pixbuf::Transforms": {
    "moar": 0e0,
    "parse": 2.828e0,
    "start": 0e0,
    "mbc": 0.001e0,
    "mast": 0.003e0,
    "ast": 0e0,
    "optimize": 0.001e0,
    "syntaxcheck": 0e0
  },
  "GTK::Roles::Signals::Generic": {
    "syntaxcheck": 0e0,
    "optimize": 0.001e0,
    "ast": 0e0,
    "mast": 0.003e0,
    "mbc": 0e0,
    "start": 0e0,
    "parse": 6.829e0,
    "moar": 0e0
  },
  "GTK::Raw::ListBox": {
    "ast": 0e0,
    "optimize": 0.002e0,
    "syntaxcheck": 0e0,
    "moar": 0e0,
    "start": 0e0,
    "parse": 5.316e0,
    "mast": 0.008e0,
    "mbc": 0.002e0
  },
  "GTK::DrawingArea": {
    "mbc": 0.001e0,
    "mast": 0.003e0,
    "moar": 0e0,
    "start": 0e0,
    "parse": 3.907e0,
    "syntaxcheck": 0e0,
    "optimize": 0.001e0,
    "ast": 0e0
  },
  "GTK::Roles::Signals::MenuShell": {
    "optimize": 0.001e0,
    "ast": 0e0,
    "syntaxcheck": 0e0,
    "moar": 0e0,
    "parse": 2.942e0,
    "start": 0e0,
    "mbc": 0e0,
    "mast": 0.003e0
  },
  "GTK::Image": {
    "moar": 0e0,
    "parse": 4.503e0,
    "start": 0e0,
    "mbc": 0.001e0,
    "mast": 0.003e0,
    "optimize": 0.001e0,
    "ast": 0e0,
    "syntaxcheck": 0e0
  },
  "GTK::TreeModelFilter": {
    "syntaxcheck": 0e0,
    "optimize": 0.002e0,
    "ast": 0e0,
    "mast": 0.008e0,
    "mbc": 0.001e0,
    "moar": 0e0,
    "start": 0e0,
    "parse": 2.972e0
  },
  "GTK::Raw::CellRendererAccel": {
    "syntaxcheck": 0e0,
    "ast": 0e0,
    "optimize": 0.002e0,
    "mast": 0.007e0,
    "mbc": 0.001e0,
    "parse": 2.666e0,
    "start": 0e0,
    "moar": 0e0
  },
  "GTK::Raw::TargetList": {
    "mast": 0.003e0,
    "mbc": 0.001e0,
    "start": 0e0,
    "parse": 3.511e0,
    "moar": 0e0,
    "syntaxcheck": 0e0,
    "optimize": 0.001e0,
    "ast": 0e0
  },
  "GTK::Offscreen": {
    "start": 0e0,
    "parse": 4.22e0,
    "moar": 0e0,
    "mast": 0.003e0,
    "mbc": 0.001e0,
    "ast": 0e0,
    "optimize": 0.001e0,
    "syntaxcheck": 0e0
  },
  "GTK::Compat::Raw::Menu": {
    "mast": 0.008e0,
    "mbc": 0.002e0,
    "moar": 0e0,
    "parse": 4.049e0,
    "start": 0e0,
    "syntaxcheck": 0e0,
    "ast": 0e0,
    "optimize": 0.002e0
  },
  "GTK::Raw::ToggleButton": {
    "ast": 0e0,
    "optimize": 0.001e0,
    "syntaxcheck": 0e0,
    "moar": 0e0,
    "start": 0e0,
    "parse": 3.334e0,
    "mbc": 0.001e0,
    "mast": 0.003e0
  },
  "GTK::Raw::ColorChooser": {
    "mast": 0.003e0,
    "mbc": 0.001e0,
    "moar": 0e0,
    "start": 0e0,
    "parse": 3.134e0,
    "syntaxcheck": 0e0,
    "ast": 0e0,
    "optimize": 0.001e0
  },
  "GTK::Roles::Signals::CellRendererAccel": {
    "optimize": 0.002e0,
    "ast": 0e0,
    "syntaxcheck": 0e0,
    "moar": 0e0,
    "parse": 2.817e0,
    "start": 0e0,
    "mbc": 0.001e0,
    "mast": 0.007e0
  },
  "GTK::Raw::ScaleButton": {
    "syntaxcheck": 0e0,
    "ast": 0e0,
    "optimize": 0.001e0,
    "mast": 0.003e0,
    "mbc": 0.001e0,
    "parse": 3.313e0,
    "start": 0e0,
    "moar": 0e0
  },
  "GTK::Menu": {
    "optimize": 0.001e0,
    "ast": 0e0,
    "syntaxcheck": 0e0,
    "start": 0e0,
    "parse": 4.693e0,
    "moar": 0e0,
    "mbc": 0.001e0,
    "mast": 0.003e0
  },
  "GTK::Roles::Signals::SpinButton": {
    "mast": 0.003e0,
    "mbc": 0e0,
    "start": 0e0,
    "parse": 2.873e0,
    "moar": 0e0,
    "syntaxcheck": 0e0,
    "optimize": 0.001e0,
    "ast": 0e0
  },
  "GTK::Raw::CellRendererProgress": {
    "moar": 0e0,
    "start": 0e0,
    "parse": 2.751e0,
    "mbc": 0.001e0,
    "mast": 0.003e0,
    "ast": 0e0,
    "optimize": 0.001e0,
    "syntaxcheck": 0e0
  },
  "GTK::Raw::FlowBox": {
    "mast": 0.004e0,
    "mbc": 0.001e0,
    "start": 0e0,
    "parse": 5.163e0,
    "moar": 0e0,
    "syntaxcheck": 0e0,
    "ast": 0e0,
    "optimize": 0.001e0
  },
  "GTK::Builder::Actionable": {
    "mast": 0.008e0,
    "mbc": 0.001e0,
    "start": 0e0,
    "parse": 2.1e0,
    "moar": 0e0,
    "syntaxcheck": 0e0,
    "ast": 0e0,
    "optimize": 0.004e0
  },
  "GTK::Compat::Raw::Pixbuf": {
    "mbc": 0.001e0,
    "mast": 0.005e0,
    "start": 0e0,
    "parse": 5.487e0,
    "moar": 0e0,
    "syntaxcheck": 0e0,
    "ast": 0e0,
    "optimize": 0.002e0
  },
  "GTK::Raw::SearchBar": {
    "mbc": 0.001e0,
    "mast": 0.003e0,
    "moar": 0e0,
    "start": 0e0,
    "parse": 3.088e0,
    "syntaxcheck": 0e0,
    "optimize": 0.001e0,
    "ast": 0e0
  },
  "GTK::Raw::InfoBar": {
    "optimize": 0.001e0,
    "ast": 0e0,
    "syntaxcheck": 0e0,
    "moar": 0e0,
    "parse": 3.659e0,
    "start": 0e0,
    "mast": 0.003e0,
    "mbc": 0.001e0
  },
  "GTK::Tooltip": {
    "ast": 0e0,
    "optimize": 0.002e0,
    "syntaxcheck": 0e0,
    "moar": 0e0,
    "parse": 2.702e0,
    "start": 0e0,
    "mbc": 0.001e0,
    "mast": 0.007e0
  },
  "GTK::Compat::Pixbuf": {
    "optimize": 0.001e0,
    "ast": 0e0,
    "syntaxcheck": 0e0,
    "moar": 0e0,
    "start": 0e0,
    "parse": 3.725e0,
    "mast": 0.003e0,
    "mbc": 0.001e0
  },
  "GTK::TextTagTable": {
    "mast": 0.003e0,
    "mbc": 0.001e0,
    "moar": 0e0,
    "start": 0e0,
    "parse": 3.065e0,
    "syntaxcheck": 0e0,
    "optimize": 0.001e0,
    "ast": 0e0
  },
  "GTK::Roles::Actionable": {
    "parse": 2.808e0,
    "start": 0e0,
    "moar": 0e0,
    "mast": 0.003e0,
    "mbc": 0e0,
    "optimize": 0.001e0,
    "ast": 0e0,
    "syntaxcheck": 0e0
  },
  "GTK::Compat::Raw::Visual": {
    "optimize": 0.002e0,
    "ast": 0e0,
    "syntaxcheck": 0e0,
    "start": 0e0,
    "parse": 3.426e0,
    "moar": 0e0,
    "mbc": 0.001e0,
    "mast": 0.008e0
  },
  "GTK::Raw::SearchEntry": {
    "optimize": 0.001e0,
    "ast": 0e0,
    "syntaxcheck": 0e0,
    "parse": 2.824e0,
    "start": 0e0,
    "moar": 0e0,
    "mbc": 0.001e0,
    "mast": 0.003e0
  },
  "GTK::Raw::FileChooserButton": {
    "mast": 0.003e0,
    "mbc": 0.001e0,
    "start": 0e0,
    "parse": 3.245e0,
    "moar": 0e0,
    "syntaxcheck": 0e0,
    "optimize": 0.001e0,
    "ast": 0e0
  },
  "GTK::Raw::TreeModelFilter": {
    "ast": 0e0,
    "optimize": 0.002e0,
    "syntaxcheck": 0e0,
    "moar": 0e0,
    "parse": 3.339e0,
    "start": 0e0,
    "mast": 0.008e0,
    "mbc": 0.001e0
  },
  "GTK::TextTag": {
    "mast": 0.003e0,
    "mbc": 0.001e0,
    "parse": 4.769e0,
    "start": 0e0,
    "moar": 0e0,
    "syntaxcheck": 0e0,
    "ast": 0e0,
    "optimize": 0.001e0
  },
  "GTK::Builder::MRO": {
    "ast": 0e0,
    "optimize": 0.002e0,
    "syntaxcheck": 0e0,
    "moar": 0e0,
    "parse": 1.518e0,
    "start": 0e0,
    "mast": 0.008e0,
    "mbc": 0.001e0
  },
  "GTK::Compat::PtrArray": {
    "moar": 0e0,
    "parse": 2.747e0,
    "start": 0e0,
    "mast": 0.008e0,
    "mbc": 0.001e0,
    "optimize": 0.002e0,
    "ast": 0e0,
    "syntaxcheck": 0e0
  },
  "GTK::Compat::Raw::Seat": {
    "parse": 2.834e0,
    "start": 0e0,
    "moar": 0e0,
    "mast": 0.007e0,
    "mbc": 0.001e0,
    "ast": 0e0,
    "optimize": 0.002e0,
    "syntaxcheck": 0e0
  },
  "GTK::Raw::Selection": {
    "ast": 0e0,
    "optimize": 0.002e0,
    "syntaxcheck": 0e0,
    "parse": 4.591e0,
    "start": 0e0,
    "moar": 0e0,
    "mbc": 0.002e0,
    "mast": 0.008e0
  },
  "GTK::Dialog::Raw::Message": {
    "syntaxcheck": 0e0,
    "ast": 0e0,
    "optimize": 0.001e0,
    "mbc": 0.001e0,
    "mast": 0.003e0,
    "start": 0e0,
    "parse": 3.288e0,
    "moar": 0e0
  },
  "GTK::TreeRowReference": {
    "moar": 0e0,
    "parse": 2.726e0,
    "start": 0e0,
    "mast": 0.008e0,
    "mbc": 0.001e0,
    "optimize": 0.002e0,
    "ast": 0e0,
    "syntaxcheck": 0e0
  },
  "GTK::CellRendererPixbuf": {
    "mbc": 0.001e0,
    "mast": 0.007e0,
    "parse": 3.081e0,
    "start": 0e0,
    "moar": 0e0,
    "syntaxcheck": 0e0,
    "optimize": 0.002e0,
    "ast": 0e0
  },
  "GTK::Compat::KeyFile": {
    "syntaxcheck": 0e0,
    "ast": 0e0,
    "optimize": 0.002e0,
    "mbc": 0.001e0,
    "mast": 0.008e0,
    "start": 0e0,
    "parse": 3.051e0,
    "moar": 0e0
  },
  "GTK::Roles::CellLayout": {
    "ast": 0e0,
    "optimize": 0.001e0,
    "syntaxcheck": 0e0,
    "parse": 3.898e0,
    "start": 0e0,
    "moar": 0e0,
    "mast": 0.003e0,
    "mbc": 0.001e0
  },
  "GTK::Dialog::ColorChooser": {
    "mast": 0.003e0,
    "mbc": 0.001e0,
    "start": 0e0,
    "parse": 4.276e0,
    "moar": 0e0,
    "syntaxcheck": 0e0,
    "ast": 0e0,
    "optimize": 0.001e0
  },
  "GTK::Raw::CellLayout": {
    "syntaxcheck": 0e0,
    "ast": 0e0,
    "optimize": 0.001e0,
    "mast": 0.003e0,
    "mbc": 0.001e0,
    "parse": 3.514e0,
    "start": 0e0,
    "moar": 0e0
  },
  "GTK::Compat::Raw::Permission": {
    "mast": 0.003e0,
    "mbc": 0.001e0,
    "moar": 0e0,
    "parse": 3.146e0,
    "start": 0e0,
    "syntaxcheck": 0e0,
    "optimize": 0.001e0,
    "ast": 0e0
  },
  "GTK::Builder::Orientable": {
    "mast": 0.008e0,
    "mbc": 0.001e0,
    "start": 0e0,
    "parse": 2.245e0,
    "moar": 0e0,
    "syntaxcheck": 0e0,
    "optimize": 0.002e0,
    "ast": 0e0
  },
  "GTK::ListBoxRow": {
    "ast": 0e0,
    "optimize": 0.002e0,
    "syntaxcheck": 0e0,
    "moar": 0e0,
    "parse": 4.109e0,
    "start": 0e0,
    "mast": 0.008e0,
    "mbc": 0.002e0
  },
  "GTK::Raw::Box": {
    "ast": 0e0,
    "optimize": 0.001e0,
    "syntaxcheck": 0e0,
    "moar": 0e0,
    "start": 0e0,
    "parse": 3.708e0,
    "mbc": 0.001e0,
    "mast": 0.003e0
  },
  "GTK::Compat::Threads": {
    "mast": 0.008e0,
    "mbc": 0.001e0,
    "start": 0e0,
    "parse": 2.578e0,
    "moar": 0e0,
    "syntaxcheck": 0e0,
    "optimize": 0.003e0,
    "ast": 0e0
  },
  "GTK::Raw::Printer": {
    "syntaxcheck": 0e0,
    "ast": 0e0,
    "optimize": 0.002e0,
    "mbc": 0.001e0,
    "mast": 0.008e0,
    "moar": 0e0,
    "parse": 4.293e0,
    "start": 0e0
  },
  "GTK::ListStore": {
    "mast": 0.004e0,
    "mbc": 0.001e0,
    "parse": 3.468e0,
    "start": 0e0,
    "moar": 0e0,
    "syntaxcheck": 0e0,
    "optimize": 0.002e0,
    "ast": 0e0
  },
  "GTK::Compat::Raw::AppInfo": {
    "ast": 0e0,
    "optimize": 0.002e0,
    "syntaxcheck": 0e0,
    "parse": 4.62e0,
    "start": 0e0,
    "moar": 0e0,
    "mbc": 0.002e0,
    "mast": 0.009e0
  },
  "GTK::StackSidebar": {
    "optimize": 0.001e0,
    "ast": 0e0,
    "syntaxcheck": 0e0,
    "moar": 0e0,
    "start": 0e0,
    "parse": 4.013e0,
    "mbc": 0.001e0,
    "mast": 0.003e0
  },
  "GTK::Roles::Signals::Editable": {
    "syntaxcheck": 0e0,
    "ast": 0e0,
    "optimize": 0.001e0,
    "mast": 0.003e0,
    "mbc": 0.001e0,
    "parse": 3.14e0,
    "start": 0e0,
    "moar": 0e0
  },
  "GTK::Roles::Signals::FlowBox": {
    "syntaxcheck": 0e0,
    "ast": 0e0,
    "optimize": 0.002e0,
    "mbc": 0.001e0,
    "mast": 0.015e0,
    "parse": 2.875e0,
    "start": 0e0,
    "moar": 0e0
  },
  "GTK::Roles::TreeDnD": {
    "mbc": 0e0,
    "mast": 0.003e0,
    "moar": 0e0,
    "start": 0e0,
    "parse": 2.836e0,
    "syntaxcheck": 0e0,
    "optimize": 0.001e0,
    "ast": 0e0
  },
  "GTK::IconTheme": {
    "mast": 0.008e0,
    "mbc": 0.001e0,
    "moar": 0e0,
    "parse": 3.189e0,
    "start": 0e0,
    "syntaxcheck": 0e0,
    "optimize": 0.002e0,
    "ast": 0e0
  },
  "GTK::Compat::MenuLinkIter": {
    "mast": 0.003e0,
    "mbc": 0.001e0,
    "start": 0e0,
    "parse": 2.565e0,
    "moar": 0e0,
    "syntaxcheck": 0e0,
    "optimize": 0.001e0,
    "ast": 0e0
  },
  "GTK::Raw::TextBuffer": {
    "ast": 0e0,
    "optimize": 0.002e0,
    "syntaxcheck": 0e0,
    "moar": 0e0,
    "start": 0e0,
    "parse": 7.129e0,
    "mbc": 0.001e0,
    "mast": 0.005e0
  },
  "GTK::Raw::ToolShell": {
    "mast": 0.003e0,
    "mbc": 0.001e0,
    "moar": 0e0,
    "parse": 3.281e0,
    "start": 0e0,
    "syntaxcheck": 0e0,
    "ast": 0e0,
    "optimize": 0.001e0
  },
  "GTK::Compat::Roles::AppInfo": {
    "mast": 0.008e0,
    "mbc": 0.003e0,
    "start": 0e0,
    "parse": 2.779e0,
    "moar": 0e0,
    "syntaxcheck": 0e0,
    "ast": 0e0,
    "optimize": 0.002e0
  },
  "GTK::Application": {
    "start": 0e0,
    "parse": 4.503e0,
    "moar": 0e0,
    "mast": 0.003e0,
    "mbc": 0.001e0,
    "ast": 0e0,
    "optimize": 0.001e0,
    "syntaxcheck": 0e0
  },
  "GTK::Raw::TextMark": {
    "mbc": 0.001e0,
    "mast": 0.013e0,
    "parse": 3.108e0,
    "start": 0e0,
    "moar": 0e0,
    "syntaxcheck": 0e0,
    "optimize": 0.002e0,
    "ast": 0e0
  },
  "GTK::Roles::Signals::Widget": {
    "start": 0e0,
    "parse": 5.749e0,
    "moar": 0e0,
    "mast": 0.003e0,
    "mbc": 0.001e0,
    "optimize": 0.001e0,
    "ast": 0e0,
    "syntaxcheck": 0e0
  },
  "GTK::Raw::Fixed": {
    "syntaxcheck": 0e0,
    "optimize": 0.001e0,
    "ast": 0e0,
    "mbc": 0.001e0,
    "mast": 0.003e0,
    "parse": 2.931e0,
    "start": 0e0,
    "moar": 0e0
  },
  "GTK::Utils::MenuBuilder": {
    "optimize": 0.002e0,
    "ast": 0e0,
    "syntaxcheck": 0e0,
    "moar": 0e0,
    "start": 0e0,
    "parse": 4.219e0,
    "mast": 0.008e0,
    "mbc": 0.001e0
  },
  "GTK::Raw::WidgetPath": {
    "mbc": 0.001e0,
    "mast": 0.004e0,
    "start": 0e0,
    "parse": 5.278e0,
    "moar": 0e0,
    "syntaxcheck": 0e0,
    "optimize": 0.001e0,
    "ast": 0e0
  },
  "GTK::Compat::Value": {
    "mast": 0.003e0,
    "mbc": 0.001e0,
    "moar": 0e0,
    "parse": 3.406e0,
    "start": 0e0,
    "syntaxcheck": 0e0,
    "ast": 0e0,
    "optimize": 0.001e0
  },
  "GTK::Compat::Raw::GList": {
    "mbc": 0.001e0,
    "mast": 0.004e0,
    "start": 0e0,
    "parse": 4.107e0,
    "moar": 0e0,
    "syntaxcheck": 0e0,
    "optimize": 0.001e0,
    "ast": 0e0
  },
  "GTK::Raw::ToggleToolButton": {
    "parse": 2.94e0,
    "start": 0e0,
    "moar": 0e0,
    "mbc": 0.001e0,
    "mast": 0.004e0,
    "ast": 0e0,
    "optimize": 0.001e0,
    "syntaxcheck": 0e0
  },
  "GTK::Raw::IconView": {
    "mast": 0.005e0,
    "mbc": 0.001e0,
    "moar": 0e0,
    "start": 0e0,
    "parse": 7.51e0,
    "syntaxcheck": 0e0,
    "optimize": 0.002e0,
    "ast": 0e0
  },
  "GTK::Raw::TreeStore": {
    "ast": 0e0,
    "optimize": 0.001e0,
    "syntaxcheck": 0e0,
    "start": 0e0,
    "parse": 4.077e0,
    "moar": 0e0,
    "mast": 0.003e0,
    "mbc": 0.001e0
  },
  "GTK::Compat::Roles::Signals": {
    "start": 0e0,
    "parse": 3.027e0,
    "moar": 0e0,
    "mast": 0.003e0,
    "mbc": 0e0,
    "ast": 0e0,
    "optimize": 0.001e0,
    "syntaxcheck": 0e0
  },
  "GTK::Compat::Roles::Signals::Device": {
    "syntaxcheck": 0e0,
    "ast": 0e0,
    "optimize": 0.002e0,
    "mbc": 0.001e0,
    "mast": 0.007e0,
    "moar": 0e0,
    "start": 0e0,
    "parse": 2.792e0
  },
  "GTK::Compat::Raw::Action": {
    "parse": 2.987e0,
    "start": 0e0,
    "moar": 0e0,
    "mbc": 0.001e0,
    "mast": 0.008e0,
    "optimize": 0.002e0,
    "ast": 0e0,
    "syntaxcheck": 0e0
  },
  "GTK::ToggleButton": {
    "syntaxcheck": 0e0,
    "ast": 0e0,
    "optimize": 0.001e0,
    "mast": 0.003e0,
    "mbc": 0.001e0,
    "moar": 0e0,
    "parse": 4.162e0,
    "start": 0e0
  },
  "GTK::Roles::Scrollable": {
    "parse": 2.908e0,
    "start": 0e0,
    "moar": 0e0,
    "mbc": 0.001e0,
    "mast": 0.003e0,
    "ast": 0e0,
    "optimize": 0.001e0,
    "syntaxcheck": 0e0
  },
  "GTK::LockButton": {
    "start": 0e0,
    "parse": 4.05e0,
    "moar": 0e0,
    "mast": 0.003e0,
    "mbc": 0.001e0,
    "optimize": 0.001e0,
    "ast": 0e0,
    "syntaxcheck": 0e0
  },
  "GTK::CellArea": {
    "mast": 0.003e0,
    "mbc": 0.001e0,
    "moar": 0e0,
    "start": 0e0,
    "parse": 4.496e0,
    "syntaxcheck": 0e0,
    "optimize": 0.001e0,
    "ast": 0e0
  },
  "GTK::IconInfo": {
    "ast": 0e0,
    "optimize": 0.001e0,
    "syntaxcheck": 0e0,
    "moar": 0e0,
    "start": 0e0,
    "parse": 3.667e0,
    "mast": 0.003e0,
    "mbc": 0.001e0
  },
  "GTK::Compat::Raw::X11_Screen": {
    "mast": 0.003e0,
    "mbc": 0.001e0,
    "moar": 0e0,
    "start": 0e0,
    "parse": 2.98e0,
    "syntaxcheck": 0e0,
    "ast": 0e0,
    "optimize": 0.001e0
  },
  "GTK::FlowBox": {
    "mast": 0.003e0,
    "mbc": 0.001e0,
    "moar": 0e0,
    "parse": 4.494e0,
    "start": 0e0,
    "syntaxcheck": 0e0,
    "optimize": 0.001e0,
    "ast": 0e0
  },
  "GTK::Compat::Raw::Screen": {
    "syntaxcheck": 0e0,
    "optimize": 0.001e0,
    "ast": 0e0,
    "mast": 0.004e0,
    "mbc": 0.001e0,
    "start": 0e0,
    "parse": 4.154e0,
    "moar": 0e0
  },
  "GTK::MenuBar": {
    "syntaxcheck": 0e0,
    "optimize": 0.001e0,
    "ast": 0e0,
    "mbc": 0.001e0,
    "mast": 0.003e0,
    "moar": 0e0,
    "parse": 4.137e0,
    "start": 0e0
  },
  "GTK::Raw::StackSwitcher": {
    "optimize": 0.001e0,
    "ast": 0e0,
    "syntaxcheck": 0e0,
    "moar": 0e0,
    "start": 0e0,
    "parse": 2.906e0,
    "mbc": 0.001e0,
    "mast": 0.003e0
  },
  "GTK::Raw::ListStore": {
    "moar": 0e0,
    "parse": 4e0,
    "start": 0e0,
    "mast": 0.004e0,
    "mbc": 0.001e0,
    "ast": 0e0,
    "optimize": 0.001e0,
    "syntaxcheck": 0e0
  },
  "GTK::Raw::MenuShell": {
    "start": 0e0,
    "parse": 3.701e0,
    "moar": 0e0,
    "mbc": 0.001e0,
    "mast": 0.003e0,
    "optimize": 0.001e0,
    "ast": 0e0,
    "syntaxcheck": 0e0
  },
  "GTK::TextMark": {
    "optimize": 0.002e0,
    "ast": 0e0,
    "syntaxcheck": 0e0,
    "moar": 0e0,
    "parse": 2.669e0,
    "start": 0e0,
    "mbc": 0.001e0,
    "mast": 0.007e0
  },
  "GTK::RadioMenuItem": {
    "moar": 0e0,
    "start": 0e0,
    "parse": 4.373e0,
    "mbc": 0.001e0,
    "mast": 0.003e0,
    "optimize": 0.001e0,
    "ast": 0e0,
    "syntaxcheck": 0e0
  },
  "GTK::Builder::Grid": {
    "ast": 0e0,
    "optimize": 0.002e0,
    "syntaxcheck": 0e0,
    "moar": 0e0,
    "parse": 2.314e0,
    "start": 0e0,
    "mast": 0.008e0,
    "mbc": 0.001e0
  },
  "GTK::Compat::Action": {
    "optimize": 0.002e0,
    "ast": 0e0,
    "syntaxcheck": 0e0,
    "moar": 0e0,
    "parse": 2.576e0,
    "start": 0e0,
    "mbc": 0.001e0,
    "mast": 0.016e0
  },
  "GTK::Raw::TreeViewColumn": {
    "optimize": 0.002e0,
    "ast": 0e0,
    "syntaxcheck": 0e0,
    "moar": 0e0,
    "start": 0e0,
    "parse": 6.202e0,
    "mast": 0.013e0,
    "mbc": 0.001e0
  },
  "GTK::Roles::Signals::IconView": {
    "optimize": 0.001e0,
    "ast": 0e0,
    "syntaxcheck": 0e0,
    "moar": 0e0,
    "start": 0e0,
    "parse": 3.232e0,
    "mbc": 0e0,
    "mast": 0.003e0
  }
}
